Workbook

Sheet Read Me
B1: Medical HRMS & Jameah — Checklist
B2: Al-Riyada College for Health Sciences · last updated 27 Oct 2026
B4: What still has to be done or checked outside the code: deploying to the live server, checks only the live server can answer, decisions only the college or the Ministry can make, HR data entry, and reviews.
B5: Work through 'Checklist'. When an item is done, set Status to Done and write the date in 'Done on'. Each row shows the task or decision it belongs to (Ref) in the Task Tracker.
B6: Every change to an item updates its 'Last updated' date and gets a line in 'Change Log' (developers: project_tracking/source, then build_all.py).
B7: Companion files in the same folder: Medical_HRMS_Jameah_Task_Tracker.xlsx (all tasks, bugs and decisions) and Medical_HRMS_Jameah_Test_Cases.xlsx (for the testing team).

Sheet Summary
A1: Summary
A2: Counts are formulas over the Checklist sheet; they update as Status changes.
A4: Group | B4: Items | C4: Open | D4: In progress | E4: Done | F4: Blocked | G4: Not needed
A5: 1. Deploy to the live server | B5: =COUNTIF(Checklist!$B$2:$B$142,$A5) | C5: =COUNTIFS(Checklist!$B$2:$B$142,$A5,Checklist!$H$2:$H$142,C$4) | D5: =COUNTIFS(Checklist!$B$2:$B$142,$A5,Checklist!$H$2:$H$142,D$4) | E5: =COUNTIFS(Checklist!$B$2:$B$142,$A5,Checklist!$H$2:$H$142,E$4) | F5: =COUNTIFS(Checklist!$B$2:$B$142,$A5,Checklist!$H$2:$H$142,F$4) | G5: =COUNTIFS(Checklist!$B$2:$B$142,$A5,Checklist!$H$2:$H$142,G$4)
A6: 2. Check on the live server | B6: =COUNTIF(Checklist!$B$2:$B$142,$A6) | C6: =COUNTIFS(Checklist!$B$2:$B$142,$A6,Checklist!$H$2:$H$142,C$4) | D6: =COUNTIFS(Checklist!$B$2:$B$142,$A6,Checklist!$H$2:$H$142,D$4) | E6: =COUNTIFS(Checklist!$B$2:$B$142,$A6,Checklist!$H$2:$H$142,E$4) | F6: =COUNTIFS(Checklist!$B$2:$B$142,$A6,Checklist!$H$2:$H$142,F$4) | G6: =COUNTIFS(Checklist!$B$2:$B$142,$A6,Checklist!$H$2:$H$142,G$4)
A7: 3. Decisions | B7: =COUNTIF(Checklist!$B$2:$B$142,$A7) | C7: =COUNTIFS(Checklist!$B$2:$B$142,$A7,Checklist!$H$2:$H$142,C$4) | D7: =COUNTIFS(Checklist!$B$2:$B$142,$A7,Checklist!$H$2:$H$142,D$4) | E7: =COUNTIFS(Checklist!$B$2:$B$142,$A7,Checklist!$H$2:$H$142,E$4) | F7: =COUNTIFS(Checklist!$B$2:$B$142,$A7,Checklist!$H$2:$H$142,F$4) | G7: =COUNTIFS(Checklist!$B$2:$B$142,$A7,Checklist!$H$2:$H$142,G$4)
A8: 4. HR data | B8: =COUNTIF(Checklist!$B$2:$B$142,$A8) | C8: =COUNTIFS(Checklist!$B$2:$B$142,$A8,Checklist!$H$2:$H$142,C$4) | D8: =COUNTIFS(Checklist!$B$2:$B$142,$A8,Checklist!$H$2:$H$142,D$4) | E8: =COUNTIFS(Checklist!$B$2:$B$142,$A8,Checklist!$H$2:$H$142,E$4) | F8: =COUNTIFS(Checklist!$B$2:$B$142,$A8,Checklist!$H$2:$H$142,F$4) | G8: =COUNTIFS(Checklist!$B$2:$B$142,$A8,Checklist!$H$2:$H$142,G$4)
A9: 5. Reviews and testing | B9: =COUNTIF(Checklist!$B$2:$B$142,$A9) | C9: =COUNTIFS(Checklist!$B$2:$B$142,$A9,Checklist!$H$2:$H$142,C$4) | D9: =COUNTIFS(Checklist!$B$2:$B$142,$A9,Checklist!$H$2:$H$142,D$4) | E9: =COUNTIFS(Checklist!$B$2:$B$142,$A9,Checklist!$H$2:$H$142,E$4) | F9: =COUNTIFS(Checklist!$B$2:$B$142,$A9,Checklist!$H$2:$H$142,F$4) | G9: =COUNTIFS(Checklist!$B$2:$B$142,$A9,Checklist!$H$2:$H$142,G$4)
A10: 6. Team and repository | B10: =COUNTIF(Checklist!$B$2:$B$142,$A10) | C10: =COUNTIFS(Checklist!$B$2:$B$142,$A10,Checklist!$H$2:$H$142,C$4) | D10: =COUNTIFS(Checklist!$B$2:$B$142,$A10,Checklist!$H$2:$H$142,D$4) | E10: =COUNTIFS(Checklist!$B$2:$B$142,$A10,Checklist!$H$2:$H$142,E$4) | F10: =COUNTIFS(Checklist!$B$2:$B$142,$A10,Checklist!$H$2:$H$142,F$4) | G10: =COUNTIFS(Checklist!$B$2:$B$142,$A10,Checklist!$H$2:$H$142,G$4)
A11: All | B11: =SUM(B5:B10) | C11: =SUM(C5:C10) | D11: =SUM(D5:D10) | E11: =SUM(E5:E10) | F11: =SUM(F5:F10) | G11: =SUM(G5:G10)

Sheet Checklist
A1: ID | B1: Group | C1: Item | D1: How / where | E1: Owner | F1: Needed by | G1: Ref (tracker) | H1: Status | I1: Done on | J1: Added on | K1: Last updated | L1: Notes
A2: CL-01 | B2: 1. Deploy to the live server | C2: Pull develop | D2: In apps/medical_hrms on the server: git fetch, then check out develop (every branch merged into it on 23 Oct; see the latest Change Log line). | E2: Server admin | F2: Before UAT | G2: HR-58, HR-71 | H2: Open | J2: 21 Oct 2026 | K2: 23 Oct 2026
A3: CL-02 | B3: 1. Deploy to the live server | C3: Migrate | D3: bench --site <site> migrate. Read the output: no errors; send any line 'Kept (they hold data ...)' to the developer (TC-ERR-05). The migrate also renames the three sick-leave types to Sick Leave 1 / 2 / 3 (balances kept, TC-LV-17). | E3: Server admin | F3: Before UAT | G3: HR-51, HR-68 | H3: Open | J3: 21 Oct 2026 | K3: 22 Oct 2026
A4: CL-03 | B4: 1. Deploy to the live server | C4: Build, clear cache, restart | D4: bench build --app medical_hrms; bench --site <site> clear-cache; bench restart. Needed for the new HR / Employee Portal, the new report and the Arabic translations. | E4: Server admin | F4: Before UAT | G4: HR-66 | H4: Open | J4: 21 Oct 2026 | K4: 21 Oct 2026
A5: CL-04 | B5: 1. Deploy to the live server | C5: Scheduler and long-queue worker running | D5: bench --site <site> doctor. The hourly Jameah refresh now runs on the long queue (about 7 minutes), so a long-queue worker must run. | E5: Server admin | F5: After deploy | G5: JM-18 | H5: Open | J5: 21 Oct 2026 | K5: 21 Oct 2026
A6: CL-05 | B6: 1. Deploy to the live server | C6: Verify the Ministry views | D6: bench --site <site> execute medical_hrms.jameah.verify.run -> all 23 views OK (5 Employee, 8 Faculty, 10 Student). | E6: Developer (Abdul Hakeem) | F6: After deploy | G6: JM-06, JM-14 | H6: Open | J6: 21 Oct 2026 | K6: 21 Oct 2026
A7: CL-06 | B7: 2. Check on the live server | C7: Error Log | D7: Open /app/error-log on the live site; group by title; note the times. This is where the client's 'random' error will show. | E7: Project owner | F7: Before UAT | G7: HR-46 | H7: Open | J7: 21 Oct 2026 | K7: 21 Oct 2026
A8: CL-07 | B8: 2. Check on the live server | C8: System e-mail account | D8: Email Account 'Notifications' -> re-enter the password -> Save -> send a test e-mail. Fixes 'Failed to decrypt key ...password'. | E8: Server admin | F8: Before UAT | G8: HR-47 | H8: Open | J8: 21 Oct 2026 | K8: 21 Oct 2026
A9: CL-08 | B9: 2. Check on the live server | C9: Logo file | D9: Open /files/rchs-logo.png on the live site; upload it again if missing. | E9: Server admin | F9: Before UAT | G9: HR-54 | H9: Open | J9: 21 Oct 2026 | K9: 21 Oct 2026
A10: CL-09 | B10: 2. Check on the live server | C10: Real HR login | D10: Log in with a real HR account (or Impersonate) and confirm the HR Portal opens. | E10: Project owner | F10: After deploy | G10: HR-45 | H10: Open | J10: 21 Oct 2026 | K10: 21 Oct 2026
A11: CL-10 | B11: 2. Check on the live server | C11: Real instructor / HOD / advisor logins | D11: Impersonate one of each and confirm their own dashboards still open. | E11: Project owner | F11: After deploy | G11: HR-45 | H11: Open | J11: 21 Oct 2026 | K11: 21 Oct 2026
A12: CL-11 | B12: 2. Check on the live server | C12: Real non-Saudi employees | D12: As HR open 2-3 real non-Saudi (Iqama) employees: no 'Not Saved' on opening; edit a field and Save. | E12: Project owner | F12: After deploy | G12: HR-63 | H12: Open | J12: 21 Oct 2026 | K12: 21 Oct 2026
A13: CL-41 | B13: 2. Check on the live server | C13: Notification e-mails | D13: After the e-mail account works (HR-47): an employee sends a request and HR rejects it with a reason; HR and the employee each get the e-mail and its link opens the request (TC-ESS-23). | E13: Testing team | F13: After HR-47 | G13: HR-25, HR-47 | H13: Open | J13: 27 Oct 2026 | K13: 27 Oct 2026
... A42: CL-39 | B42: 5. Reviews and testing | C42: Round 2 document to the testing team | D42: Put Round 2 on their test server first (CL-01, migrate), then give them docs/guides/Medical_HRMS_Round_2_Whats_New.pdf and the Test Cases workbook (filter Round = Round 2). | E42: Project owner | F42: Now | G42: HR-76 | H42: Open | J42: 27 Oct 2026 | K42: 27 Oct 2026

Sheet Change Log
A1: Date | B1: Area | C1: Items | D1: What changed | E1: By
A2: 27 Oct 2026 | B2: Testing | C2: HR-76 | D2: QA cleanup stops the unsent e-mails of removed QA records (status Error) instead of deleting them: the e-mail job could be sending them at that moment and logged 'Email Queue ... not found'. | E2: Abdul Hakeem
A3: 27 Oct 2026 | B3: Round 2 | C3: HR-16, HR-24, HR-25, HR-48, HR-76, HR-77, B-26, B-56, B-57, DEC-16, CL-39 - CL-41, TC-APR-02, TC-APR-09 - TC-APR-13, TC-ESS-17 - TC-ESS-23, TC-EMP-13, TC-EMP-14, TC-LV-18 | D3: Round 2: employees change, send or delete their drafts and send a rejected request again; rejecting needs a reason, which the employee reads with the request's history; notifications in the bell (and e-mail where the mail account works) for HR on new requests and for the employee at every later step; the Instructor and Academic Advisor forms save after an Employee is picked (B-26, B-56); amounts say SAR; the bell shows the time as text (B-57). New: Round column in the Test Cases workbook, the Round 2 document for the testers, User Guide and Installation Guide updated. Re-tested: 101/101 browser checks, 52 unit tests (0 failures), 0 file and 0 site problems, 31 server methods x 3 roles; Error Log: only the known e-mail password error B-25 (notification e-mails this copy cannot send). | E3: Abdul Hakeem
A4: 27 Oct 2026 | B4: Testing | C4: HR-75, CL-23, CL-37 | D4: Test Cases workbook and both PDF guides given to the testing team; their UAT round has started (HR-75 In progress). Checklist: new status 'In progress' (blue); CL-23 Run the test cases and CL-37 Share the guides are In progress (the guides still go to HR, managers and the server admin). Testing team added to the Assigned to list. | E4: Abdul Hakeem
A5: 23 Oct 2026 | B5: Documentation | C5: HR-37, HR-38, DEC-15, CL-38 | D5: Academic Presence (HR requirements 1-4) checked against the client's request: all four are on the HR Dashboard and tested. The guides now say where each tab's data comes from, that Proctor Schedules stays empty until exam committees are entered (new Checklist CL-38), that Students on Campus counts by hour, and that after-4 PM times come from the timetable and class attendance until devices are connected. New decision DEC-15: hour slots or the college's own periods. | E5: Abdul Hakeem
A6: 23 Oct 2026 | B6: Documentation | C6: HR-74, B-54, B-55, TC-ESS-02, TC-ESS-04, TC-ESS-16, CL-37 | D6: Installation and Setup Guide (21 pages) and User Guide (30 pages) in PDF, with screenshots from the test site (QA data only); sources in docs/guides/src. Fixed while writing them: Remote Work Request duration and Permission Request hours were always 0 (now counted; reversed times refused; a patch fills in saved requests). Re-tested: 95/95 browser checks, 42 unit tests (0 failures), 0 file and 0 site problems, 29 server methods x 3 roles, no Error Log entries. | E6: Abdul Hakeem
A7: 23 Oct 2026 | B7: Project tracking | C7: All tasks; HR-04 - HR-06, HR-11, HR-12, HR-28 - HR-30, HR-48, HR-66, HR-70, HR-71, HR-73, JM-03, JM-06, JM-12, JM-13, JM-16, JM-17, B-26, B-34, CL-35 | D7: Owners corrected: Abdul Hakeem designed and built Medical HRMS and Jameah and leads every development task. New column 'Assigned to' (with a dropdown) shows who a task was given to: Dinesh (HR-06, and HR-04 at first), Fathir (HR-04, HR-05, HR-70), otherwise Abdul Hakeem; client-side tasks stay with HR, Academic Affairs, the Registrar or the server admin. Wording that credited others for this work removed. Status and Priority shown in clear colours in all three workbooks (Status, Priority, Result and Severity cells only), with a priority legend in the Read Me. | E7: Abdul Hakeem
A8: 23 Oct 2026 | B8: Project tracking | C8: HR-72, B-52, B-53 | D8: The three check scripts (files, site, server methods) now record their result in the Test Cases workbook (Last automated run: Pass, 23 Oct). The file check found a missing import in the site check; fixed. | E8: Abdul Hakeem
A9: 23 Oct 2026 | B9: Medical HRMS | C9: HR-58, HR-69, HR-71 - HR-73, B-45 - B-51, CL-01, CL-30, CL-34 - CL-36, TC-ERR-06 - TC-ERR-09, TC-SEC-10 | D9: Every branch merged into develop (ministry-lookup last; employee-applicant recorded as merged without its July files, as decided); develop is now the branch to test and deploy. Full check of every file and page (files, site, server methods by role, unit tests, browser suite with a sweep of every Medical HRMS doctype); checks kept in tests/checks. Fixed: stray files, outdated README and developer guide, QA setup race, refresh-lock test, Ministry code search. HR-69 corrected (employee counts were test hires). Result: 95/95 browser checks (error sweep: 116 pages for HR, 20 for employees), 37/37 unit tests, 23/23 Ministry views, 29 server methods x 3 roles, 0 file and 0 site problems, no Error Log entries. | E9: Abdul Hakeem
A10: 22 Oct 2026 | B10: Medical HRMS | C10: HR-58, HR-70, JM-05, JM-19, B-42 – B-44, TC-REC-13, TC-REC-14 | D10: develop (Fathir's job application update, PR #2) merged into feature/uat-2026-10-22; conflicts in job_application.py, job-application.html and ar.csv resolved keeping both sides; the Appreciation list restored and the work extension accepted again on the updated form (B-42, B-44); a migrate no longer fails when it overlaps the hourly Jameah refresh (B-43); test output removed from the repository. Re-tested: 95/95 browser checks, 37/37 unit tests, 23/23 Ministry views OK, no Error Log entries. Branch to test and deploy: feature/uat-2026-10-22. | E10: Abdul Hakeem
A11: 22 Oct 2026 | B11: Medical HRMS | C11: HR-08, HR-09, HR-19, HR-20, HR-22, HR-68, HR-69, B-36 – B-40, DEC-14, CL-28 – CL-33 | D11: Leave made one flow: Leave Plan (employees send it; manager and department head approve) -> Leave Application (only leave the employee holds, with the days left; Apply now from an approved plan) -> Leave Return (asked for when a leave ends; certificate and occupational health only after sick leave). Sick-leave types renamed in pay order (Sick Leave 1 / 2 / 3) by a migration patch. HR Portal Leave section: setup check per company, daily leave counts, yearly setup in order. Arabic for 114 new texts. 5 unit tests and 7 browser tests (LV-01 - LV-07); test cases TC-LV-09 - 17, TC-HRD-06/07. Real company Al Riyada College still needs its leave setup (HR-69). Branch to test and deploy: feature/uat-2026-10-22 (all work to date). | E11: Abdul Hakeem
A12: 22 Oct 2026 | B12: Testing | C12: HR-67, B-41 | D12: Browser test suite, QA data scripts and the results helper kept in the repository (tests/e2e); the QA scripts only run on a site named in QA_TEST_SITE. The QA reset no longer leaves the QA HR User without access to its own My Settings (test data only). The leave unit test now attaches a real test file, so it no longer writes 'Error Attaching File' to the Error Log. Full run 22 Oct: 95/95 browser checks, 36/36 unit tests, 23/23 Ministry views OK, no new Error Log entries. | E12: Abdul Hakeem
... A18: 1 Oct 2026 | B18: Medical HRMS | C18: HR-01 – HR-32 | D18: First HRM task tracker (HRM_TASK_TRACKER.md / .csv). | E18: Team
