Workbook

Sheet Read Me
B1: Medical HRMS & Jameah — Test Cases
B2: For the testing team · last updated 23 Oct 2026 · last automated run 23 Oct 2026 06:20 AST (95/95 browser checks passed)
B4: How to use
B5: 1. Use the test site (not live data) and the accounts in 'Test Accounts'.
B6: 2. Work through 'Test Cases' top to bottom. Fill the yellow columns: Result, Tested By, Test Date, Actual Result / Notes, Bug ID.
B7: 3. Every Fail or error pop-up gets a row in 'Bug Report' — with the exact date and time, the page address and the exact message. The client sees an error at unknown times, so the time and page are the most important facts.
B8: 4. 'Summary' counts results by module automatically.
B9: 5. What is left to check or decide outside the test cases (live server, decisions, HR data) is in Medical_HRMS_Jameah_Checklist.xlsx in the same folder.
B10: Every change to a case updates its 'Last updated' date and gets a line in 'Change Log' (developers: project_tracking/source, then build_all.py).
B12: Columns
B13: Last automated run | C13: Result of the same check in the developer's automated run (browser suite, or a tests/checks script for file / site / server-method checks). A case can pass there and still fail for you — please test it anyway.
B14: Priority | C14: Critical: blocks go-live. High: must work for UAT. Medium / Low: fix before or soon after go-live.
B15: Type | C15: Functional, Negative (wrong input must be refused), Security, Regression (a bug that was fixed), Usability, Monitoring, Data.
B17: Result values
B18: Not run
B19: Pass
B20: Fail
B21: Blocked
B22: N/A

Sheet Summary
A1: Test summary
A2: Counts are formulas over the Test Cases sheet; they update as testers fill the Result column.
A4: Module | B4: Cases | C4: Not run | D4: Pass | E4: Fail | F4: Blocked | G4: N/A | H4: % passed (of run) | I4: Critical not passed
A5: Login & landing | B5: =COUNTIF('Test Cases'!$B$2:$B$330,$A5) | C5: =COUNTIFS('Test Cases'!$B$2:$B$330,$A5,'Test Cases'!$M$2:$M$330,C$4) | D5: =COUNTIFS('Test Cases'!$B$2:$B$330,$A5,'Test Cases'!$M$2:$M$330,D$4) | E5: =COUNTIFS('Test Cases'!$B$2:$B$330,$A5,'Test Cases'!$M$2:$M$330,E$4) | F5: =COUNTIFS('Test Cases'!$B$2:$B$330,$A5,'Test Cases'!$M$2:$M$330,F$4) | G5: =COUNTIFS('Test Cases'!$B$2:$B$330,$A5,'Test Cases'!$M$2:$M$330,G$4) | H5: =IFERROR(D5/(D5+E5+F5),"-") | I5: =COUNTIFS('Test Cases'!$B$2:$B$330,$A5,'Test Cases'!$I$2:$I$330,"Critical")-COUNTIFS('Test Cases'!$B$2:$B$330,$A5,'Test Cases'!$I$2:$I$330,"Critical",'Test Cases'!$M$2:$M$330,"Pass")
A6: HR Dashboard | B6: =COUNTIF('Test Cases'!$B$2:$B$330,$A6) | C6: =COUNTIFS('Test Cases'!$B$2:$B$330,$A6,'Test Cases'!$M$2:$M$330,C$4) | D6: =COUNTIFS('Test Cases'!$B$2:$B$330,$A6,'Test Cases'!$M$2:$M$330,D$4) | E6: =COUNTIFS('Test Cases'!$B$2:$B$330,$A6,'Test Cases'!$M$2:$M$330,E$4) | F6: =COUNTIFS('Test Cases'!$B$2:$B$330,$A6,'Test Cases'!$M$2:$M$330,F$4) | G6: =COUNTIFS('Test Cases'!$B$2:$B$330,$A6,'Test Cases'!$M$2:$M$330,G$4) | H6: =IFERROR(D6/(D6+E6+F6),"-") | I6: =COUNTIFS('Test Cases'!$B$2:$B$330,$A6,'Test Cases'!$I$2:$I$330,"Critical")-COUNTIFS('Test Cases'!$B$2:$B$330,$A6,'Test Cases'!$I$2:$I$330,"Critical",'Test Cases'!$M$2:$M$330,"Pass")
A7: Employee self-service | B7: =COUNTIF('Test Cases'!$B$2:$B$330,$A7) | C7: =COUNTIFS('Test Cases'!$B$2:$B$330,$A7,'Test Cases'!$M$2:$M$330,C$4) | D7: =COUNTIFS('Test Cases'!$B$2:$B$330,$A7,'Test Cases'!$M$2:$M$330,D$4) | E7: =COUNTIFS('Test Cases'!$B$2:$B$330,$A7,'Test Cases'!$M$2:$M$330,E$4) | F7: =COUNTIFS('Test Cases'!$B$2:$B$330,$A7,'Test Cases'!$M$2:$M$330,F$4) | G7: =COUNTIFS('Test Cases'!$B$2:$B$330,$A7,'Test Cases'!$M$2:$M$330,G$4) | H7: =IFERROR(D7/(D7+E7+F7),"-") | I7: =COUNTIFS('Test Cases'!$B$2:$B$330,$A7,'Test Cases'!$I$2:$I$330,"Critical")-COUNTIFS('Test Cases'!$B$2:$B$330,$A7,'Test Cases'!$I$2:$I$330,"Critical",'Test Cases'!$M$2:$M$330,"Pass")
A8: Leave | B8: =COUNTIF('Test Cases'!$B$2:$B$330,$A8) | C8: =COUNTIFS('Test Cases'!$B$2:$B$330,$A8,'Test Cases'!$M$2:$M$330,C$4) | D8: =COUNTIFS('Test Cases'!$B$2:$B$330,$A8,'Test Cases'!$M$2:$M$330,D$4) | E8: =COUNTIFS('Test Cases'!$B$2:$B$330,$A8,'Test Cases'!$M$2:$M$330,E$4) | F8: =COUNTIFS('Test Cases'!$B$2:$B$330,$A8,'Test Cases'!$M$2:$M$330,F$4) | G8: =COUNTIFS('Test Cases'!$B$2:$B$330,$A8,'Test Cases'!$M$2:$M$330,G$4) | H8: =IFERROR(D8/(D8+E8+F8),"-") | I8: =COUNTIFS('Test Cases'!$B$2:$B$330,$A8,'Test Cases'!$I$2:$I$330,"Critical")-COUNTIFS('Test Cases'!$B$2:$B$330,$A8,'Test Cases'!$I$2:$I$330,"Critical",'Test Cases'!$M$2:$M$330,"Pass")
A9: HR approvals | B9: =COUNTIF('Test Cases'!$B$2:$B$330,$A9) | C9: =COUNTIFS('Test Cases'!$B$2:$B$330,$A9,'Test Cases'!$M$2:$M$330,C$4) | D9: =COUNTIFS('Test Cases'!$B$2:$B$330,$A9,'Test Cases'!$M$2:$M$330,D$4) | E9: =COUNTIFS('Test Cases'!$B$2:$B$330,$A9,'Test Cases'!$M$2:$M$330,E$4) | F9: =COUNTIFS('Test Cases'!$B$2:$B$330,$A9,'Test Cases'!$M$2:$M$330,F$4) | G9: =COUNTIFS('Test Cases'!$B$2:$B$330,$A9,'Test Cases'!$M$2:$M$330,G$4) | H9: =IFERROR(D9/(D9+E9+F9),"-") | I9: =COUNTIFS('Test Cases'!$B$2:$B$330,$A9,'Test Cases'!$I$2:$I$330,"Critical")-COUNTIFS('Test Cases'!$B$2:$B$330,$A9,'Test Cases'!$I$2:$I$330,"Critical",'Test Cases'!$M$2:$M$330,"Pass")
A10: Security & privacy | B10: =COUNTIF('Test Cases'!$B$2:$B$330,$A10) | C10: =COUNTIFS('Test Cases'!$B$2:$B$330,$A10,'Test Cases'!$M$2:$M$330,C$4) | D10: =COUNTIFS('Test Cases'!$B$2:$B$330,$A10,'Test Cases'!$M$2:$M$330,D$4) | E10: =COUNTIFS('Test Cases'!$B$2:$B$330,$A10,'Test Cases'!$M$2:$M$330,E$4) | F10: =COUNTIFS('Test Cases'!$B$2:$B$330,$A10,'Test Cases'!$M$2:$M$330,F$4) | G10: =COUNTIFS('Test Cases'!$B$2:$B$330,$A10,'Test Cases'!$M$2:$M$330,G$4) | H10: =IFERROR(D10/(D10+E10+F10),"-") | I10: =COUNTIFS('Test Cases'!$B$2:$B$330,$A10,'Test Cases'!$I$2:$I$330,"Critical")-COUNTIFS('Test Cases'!$B$2:$B$330,$A10,'Test Cases'!$I$2:$I$330,"Critical",'Test Cases'!$M$2:$M$330,"Pass")
A11: Employee master & Ministry fields | B11: =COUNTIF('Test Cases'!$B$2:$B$330,$A11) | C11: =COUNTIFS('Test Cases'!$B$2:$B$330,$A11,'Test Cases'!$M$2:$M$330,C$4) | D11: =COUNTIFS('Test Cases'!$B$2:$B$330,$A11,'Test Cases'!$M$2:$M$330,D$4) | E11: =COUNTIFS('Test Cases'!$B$2:$B$330,$A11,'Test Cases'!$M$2:$M$330,E$4) | F11: =COUNTIFS('Test Cases'!$B$2:$B$330,$A11,'Test Cases'!$M$2:$M$330,F$4) | G11: =COUNTIFS('Test Cases'!$B$2:$B$330,$A11,'Test Cases'!$M$2:$M$330,G$4) | H11: =IFERROR(D11/(D11+E11+F11),"-") | I11: =COUNTIFS('Test Cases'!$B$2:$B$330,$A11,'Test Cases'!$I$2:$I$330,"Critical")-COUNTIFS('Test Cases'!$B$2:$B$330,$A11,'Test Cases'!$I$2:$I$330,"Critical",'Test Cases'!$M$2:$M$330,"Pass")
A12: Medical licences | B12: =COUNTIF('Test Cases'!$B$2:$B$330,$A12) | C12: =COUNTIFS('Test Cases'!$B$2:$B$330,$A12,'Test Cases'!$M$2:$M$330,C$4) | D12: =COUNTIFS('Test Cases'!$B$2:$B$330,$A12,'Test Cases'!$M$2:$M$330,D$4) | E12: =COUNTIFS('Test Cases'!$B$2:$B$330,$A12,'Test Cases'!$M$2:$M$330,E$4) | F12: =COUNTIFS('Test Cases'!$B$2:$B$330,$A12,'Test Cases'!$M$2:$M$330,F$4) | G12: =COUNTIFS('Test Cases'!$B$2:$B$330,$A12,'Test Cases'!$M$2:$M$330,G$4) | H12: =IFERROR(D12/(D12+E12+F12),"-") | I12: =COUNTIFS('Test Cases'!$B$2:$B$330,$A12,'Test Cases'!$I$2:$I$330,"Critical")-COUNTIFS('Test Cases'!$B$2:$B$330,$A12,'Test Cases'!$I$2:$I$330,"Critical",'Test Cases'!$M$2:$M$330,"Pass")
A13: Recruitment | B13: =COUNTIF('Test Cases'!$B$2:$B$330,$A13) | C13: =COUNTIFS('Test Cases'!$B$2:$B$330,$A13,'Test Cases'!$M$2:$M$330,C$4) | D13: =COUNTIFS('Test Cases'!$B$2:$B$330,$A13,'Test Cases'!$M$2:$M$330,D$4) | E13: =COUNTIFS('Test Cases'!$B$2:$B$330,$A13,'Test Cases'!$M$2:$M$330,E$4) | F13: =COUNTIFS('Test Cases'!$B$2:$B$330,$A13,'Test Cases'!$M$2:$M$330,F$4) | G13: =COUNTIFS('Test Cases'!$B$2:$B$330,$A13,'Test Cases'!$M$2:$M$330,G$4) | H13: =IFERROR(D13/(D13+E13+F13),"-") | I13: =COUNTIFS('Test Cases'!$B$2:$B$330,$A13,'Test Cases'!$I$2:$I$330,"Critical")-COUNTIFS('Test Cases'!$B$2:$B$330,$A13,'Test Cases'!$I$2:$I$330,"Critical",'Test Cases'!$M$2:$M$330,"Pass")
A14: Academic presence | B14: =COUNTIF('Test Cases'!$B$2:$B$330,$A14) | C14: =COUNTIFS('Test Cases'!$B$2:$B$330,$A14,'Test Cases'!$M$2:$M$330,C$4) | D14: =COUNTIFS('Test Cases'!$B$2:$B$330,$A14,'Test Cases'!$M$2:$M$330,D$4) | E14: =COUNTIFS('Test Cases'!$B$2:$B$330,$A14,'Test Cases'!$M$2:$M$330,E$4) | F14: =COUNTIFS('Test Cases'!$B$2:$B$330,$A14,'Test Cases'!$M$2:$M$330,F$4) | G14: =COUNTIFS('Test Cases'!$B$2:$B$330,$A14,'Test Cases'!$M$2:$M$330,G$4) | H14: =IFERROR(D14/(D14+E14+F14),"-") | I14: =COUNTIFS('Test Cases'!$B$2:$B$330,$A14,'Test Cases'!$I$2:$I$330,"Critical")-COUNTIFS('Test Cases'!$B$2:$B$330,$A14,'Test Cases'!$I$2:$I$330,"Critical",'Test Cases'!$M$2:$M$330,"Pass")
A15: Jameah (Ministry) | B15: =COUNTIF('Test Cases'!$B$2:$B$330,$A15) | C15: =COUNTIFS('Test Cases'!$B$2:$B$330,$A15,'Test Cases'!$M$2:$M$330,C$4) | D15: =COUNTIFS('Test Cases'!$B$2:$B$330,$A15,'Test Cases'!$M$2:$M$330,D$4) | E15: =COUNTIFS('Test Cases'!$B$2:$B$330,$A15,'Test Cases'!$M$2:$M$330,E$4) | F15: =COUNTIFS('Test Cases'!$B$2:$B$330,$A15,'Test Cases'!$M$2:$M$330,F$4) | G15: =COUNTIFS('Test Cases'!$B$2:$B$330,$A15,'Test Cases'!$M$2:$M$330,G$4) | H15: =IFERROR(D15/(D15+E15+F15),"-") | I15: =COUNTIFS('Test Cases'!$B$2:$B$330,$A15,'Test Cases'!$I$2:$I$330,"Critical")-COUNTIFS('Test Cases'!$B$2:$B$330,$A15,'Test Cases'!$I$2:$I$330,"Critical",'Test Cases'!$M$2:$M$330,"Pass")
A16: Errors & monitoring | B16: =COUNTIF('Test Cases'!$B$2:$B$330,$A16) | C16: =COUNTIFS('Test Cases'!$B$2:$B$330,$A16,'Test Cases'!$M$2:$M$330,C$4) | D16: =COUNTIFS('Test Cases'!$B$2:$B$330,$A16,'Test Cases'!$M$2:$M$330,D$4) | E16: =COUNTIFS('Test Cases'!$B$2:$B$330,$A16,'Test Cases'!$M$2:$M$330,E$4) | F16: =COUNTIFS('Test Cases'!$B$2:$B$330,$A16,'Test Cases'!$M$2:$M$330,F$4) | G16: =COUNTIFS('Test Cases'!$B$2:$B$330,$A16,'Test Cases'!$M$2:$M$330,G$4) | H16: =IFERROR(D16/(D16+E16+F16),"-") | I16: =COUNTIFS('Test Cases'!$B$2:$B$330,$A16,'Test Cases'!$I$2:$I$330,"Critical")-COUNTIFS('Test Cases'!$B$2:$B$330,$A16,'Test Cases'!$I$2:$I$330,"Critical",'Test Cases'!$M$2:$M$330,"Pass")
A17: All modules | B17: =SUM(B5:B16) | C17: =SUM(C5:C16) | D17: =SUM(D5:D16) | E17: =SUM(E5:E16) | F17: =SUM(F5:F16) | G17: =SUM(G5:G16) | H17: =IFERROR(D17/(D17+E17+F17),"-") | I17: =SUM(I5:I16)
A19: Last automated run (developer)
A20: Pass | B20: =COUNTIF('Test Cases'!$L$2:$L$330,"Pass")
A21: Fail | B21: =COUNTIF('Test Cases'!$L$2:$L$330,"Fail")
A22: Manual only / unit test | B22: =COUNTA('Test Cases'!$L$2:$L$130)-B20-B21

Sheet Test Cases
A1: TC ID | B1: Module | C1: Scenario | D1: Login / role | E1: Preconditions | F1: Steps | G1: Test data | H1: Expected result | I1: Priority | J1: Type | K1: Automated test | L1: Last automated run | M1: Result | N1: Tested by | O1: Test date | P1: Actual result / notes | Q1: Bug ID | R1: Added on | S1: Last updated
A2: TC-LGN-01 | B2: Login & landing | C2: HR Manager lands on the HR Dashboard | D2: HR Manager | E2: HR Manager login exists. | F2: 1. Open /login. 2. Enter HR Manager e-mail and password. 3. Click Login. | G2: HR Manager account | H2: The HR Dashboard opens (/app/hr-dashboard) showing 'Welcome back, HR Team'. No error pop-up. | I2: Critical | J2: Functional | K2: LGN-01 | L2: Pass | M2: Not run | R2: 21 Oct 2026 | S2: 21 Oct 2026
A3: TC-LGN-02 | B3: Login & landing | C3: HR User lands on the HR Dashboard | D3: HR User | E3: HR User login exists. | F3: Same as TC-LGN-01 with the HR User account. | G3: HR User account | H3: HR Dashboard opens. | I3: High | J3: Functional | K3: LGN-02 | L3: Pass | M3: Not run | R3: 21 Oct 2026 | S3: 21 Oct 2026
A4: TC-LGN-03 | B4: Login & landing | C4: Employee lands on the Employee Dashboard | D4: Employee | E4: Employee login linked to an Employee record. | F4: Log in as the employee. | G4: Employee account | H4: Employee Dashboard opens with their name and Employee ID. | I4: Critical | J4: Functional | K4: LGN-03 | L4: Pass | M4: Not run | R4: 21 Oct 2026 | S4: 21 Oct 2026
A5: TC-LGN-04 | B5: Login & landing | C5: Instructor keeps the Instructor dashboard | D5: Instructor | E5: Instructor login. | F5: Log in as the instructor. | G5: Instructor account | H5: Instructor Portal opens (not the HR or Employee dashboard). | I5: High | J5: Regression | K5: LGN-04 | L5: Pass | M5: Not run | R5: 21 Oct 2026 | S5: 21 Oct 2026
A6: TC-LGN-05 | B6: Login & landing | C6: Opening /app again returns to the user's dashboard | D6: HR Manager | E6: Logged in. | F6: 1. Open a new browser tab. 2. Go to /app. | G6: — | H6: The same dashboard opens again. | I6: Medium | J6: Functional | K6: LGN-01..04 | L6: Pass | M6: Not run | R6: 21 Oct 2026 | S6: 21 Oct 2026
A7: TC-LGN-06 | B7: Login & landing | C7: Wrong password | D7: Applicant (not logged in) | E7: — | F7: 1. Open /login. 2. Enter a valid e-mail and a wrong password. 3. Click Login. | G7: Wrong password | H7: An 'invalid login' message; stays on the login page. | I7: Medium | J7: Negative | K7: LGN-05 | L7: Pass | M7: Not run | R7: 21 Oct 2026 | S7: 21 Oct 2026
A8: TC-LGN-07 | B8: Login & landing | C8: Logout and log in as a different role | D8: HR Manager | E8: Logged in as HR. | F8: 1. Log out. 2. Log in as an employee. | G8: Two accounts | H8: Employee lands on the Employee Dashboard; no HR pages are shown. | I8: Medium | J8: Functional | K8: — | L8: Manual only | M8: Not run | R8: 21 Oct 2026 | S8: 21 Oct 2026
A9: TC-LGN-08 | B9: Login & landing | C9: Breadcrumbs never lead to 'Not permitted' | D9: Employee | E9: Logged in as an employee. | F9: 1. Open the Employee Dashboard, Leave Application list and a request list. 2. Click every link in the top bar next to the logo (breadcrumbs). | G9: — | H9: Each breadcrumb opens a page the employee can see (e.g. Employee Self Service). Never 'Not permitted'. | I9: High | J9: Regression | K9: NAV-01 | L9: Pass | M9: Not run | R9: 21 Oct 2026 | S9: 21 Oct 2026
A10: TC-LGN-09 | B10: Login & landing | C10: HR breadcrumbs | D10: HR Manager | E10: Logged in as HR. | F10: Same as TC-LGN-08 as HR. | G10: — | H10: Breadcrumbs open (Medical HRMS, HR...). | I10: Medium | J10: Regression | K10: NAV-02 | L10: Pass | M10: Not run | R10: 21 Oct 2026 | S10: 21 Oct 2026
A11: TC-LGN-10 | B11: Login & landing | C11: New portal design: menu, top bar, heading | D11: HR Manager | E11: Logged in as HR. | F11: 1. Look at the left menu, the top bar and the heading. 2. Open each menu section (Employee Requests, Leave ...) and a few pages from it. 3. Click 'Collapse menu', then expand it again. | G11: — | H11: Same style as the Instructor Portal: dark-green menu with sections, breadcrumb 'HR Portal / Dashboard', EN/AR, moon icon, bell and initials on the top bar. Every menu page opens (no 'Not permitted'). | I11: High | J11: Functional | K11: HRD-03 | L11: Pass | M11: Not run | R11: 21 Oct 2026 | S11: 21 Oct 2026
A12: TC-LGN-11 | B12: Login & landing | C12: Employee Portal menu actions | D12: Employee | E12: Logged in as an employee. | F12: 1. Menu > New Request > Permission Request. 2. Menu > My Leave and Recent Requests. 3. Menu > My Profile. | G12: — | H12: 1 opens the Permission Request form; 2 scrolls to that section; 3 shows your profile. No HR entries in the menu. | I12: High | J12: Functional | K12: SHL-01 | L12: Pass | M12: Not run | R12: 21 Oct 2026 | S12: 21 Oct 2026
A13: TC-LGN-12 | B13: Login & landing | C13: Dark mode and Arabic from the top bar | D13: Employee | E13: Logged in. | F13: 1. Click the moon icon; click it again. 2. Click AR; check the page; click EN. | G13: — | H13: Dark mode switches on and off. In Arabic the menu moves to the right and labels are in Arabic; EN switches back. | I13: Medium | J13: Functional | K13: SHL-05 | L13: Pass | M13: Not run | R13: 21 Oct 2026 | S13: 21 Oct 2026
... A130: TC-ERR-09 | B130: Errors & monitoring | C130: Every hook, doctype and record is valid on the site | D130: Developer | E130: Site migrated. | F130: ../../env/bin/python tests/e2e/fx.py tests/checks/site.py | G130: — | H130: PROBLEMS: 0; every hook, patch and asset resolves; saved records pass validation. | I130: High | J130: Regression | K130: tests/checks/site.py | L130: Pass | M130: Not run | R130: 23 Oct 2026 | S130: 23 Oct 2026

Sheet Bug Report
A1: Bug ID | B1: Date & time seen | C1: Login (user) | D1: Role | E1: Page address (URL) | F1: What you were doing (steps) | G1: Exact error message | H1: Screenshot file name | I1: Browser / device | J1: Severity | K1: TC ID | L1: Status | M1: Developer notes
A2: BUG-001 | B2: 2026-10-22 10:35 | C2: hr.user@alriyada.edu.sa | D2: HR User | E2: https://<site>/app/leave-application/HR-LAP-2026-00012 | F2: Opened the leave, set Status to Approved, clicked Save | G2: Example: 'Insufficient Permission for Leave Application' (red pop-up) | H2: bug-001.png | I2: Chrome 130 / Windows | J2: High | K2: TC-LV-02 | L2: Open | M2: Example row — replace with real reports

Sheet Test Accounts
A1: Role | B1: What it is for | C1: Account on the test site | D1: Notes
A2: HR Manager | B2: HR Dashboard, approvals, recruitment, Jameah pages | C2: Ask the developer (QA accounts are created per test run) | D2: Must have HR Manager + HR User roles
A3: HR User | B3: Day-to-day HR checks | C3: Ask the developer | D3: HR User role only
A4: Employee (x2) | B4: Self-service and privacy checks (two people) | C4: Ask the developer | D4: Each must be linked to an Employee record with a leave approver
A5: Instructor | B5: Check the Instructor dashboard is not affected | C5: qa.instructor@rchs-qa.test / QaInstructor#2026 | D5: Local test site only
A6: Academic Affairs (Education Manager) | B6: Jameah Settings and Code Map | C6: Ask the developer | D6: Education Manager role
A7: Administrator | B7: Error Log, e-mail account, scheduled jobs | C7: Site administrator | D7: Never use for normal test cases
A8: Applicant | B8: Public job application form | C8: No login — use the generated link | D8: Use test e-mails, never real people

Sheet Change Log
A1: Date | B1: Area | C1: Items | D1: What changed | E1: By
A2: 23 Oct 2026 | B2: Project tracking | C2: HR-04 - HR-06, HR-11, HR-28 - HR-30, HR-48, HR-66, HR-70, JM-12, JM-13, JM-16, JM-17, B-26 | D2: Owners corrected: Medical HRMS and Jameah are built by the HRMS team only, so no task is owned by the Education team (HR-11, HR-28, HR-48, JM-16, JM-17 now Abdul Hakeem; JM-12 Academic Affairs + Abdul Hakeem; JM-13 Registrar). Employee application: Dinesh + Abdul Hakeem built it (HR-06); Fathir handles its UI (HR-70) and Dinesh's open items (HR-04, HR-05). Status and Priority shown in clear colours in all three workbooks (Status, Priority, Result and Severity cells only), with a priority legend in the Read Me. | E2: Abdul Hakeem
A3: 23 Oct 2026 | B3: Project tracking | C3: HR-72, B-52, B-53 | D3: The three check scripts (files, site, server methods) now record their result in the Test Cases workbook (Last automated run: Pass, 23 Oct). The file check found a missing import in the site check; fixed. | E3: Abdul Hakeem
A4: 23 Oct 2026 | B4: Medical HRMS | C4: HR-58, HR-69, HR-71 - HR-73, B-45 - B-51, CL-01, CL-30, CL-34 - CL-36, TC-ERR-06 - TC-ERR-09, TC-SEC-10 | D4: Every branch merged into develop (ministry-lookup last; employee-applicant recorded as merged without its July files, as decided); develop is now the branch to test and deploy. Full check of every file and page (files, site, server methods by role, unit tests, browser suite with a sweep of every Medical HRMS doctype); checks kept in tests/checks. Fixed: stray files, outdated README and developer guide, QA setup race, refresh-lock test, Ministry code search. HR-69 corrected (employee counts were test hires). Result: 95/95 browser checks (error sweep: 116 pages for HR, 20 for employees), 37/37 unit tests, 23/23 Ministry views, 29 server methods x 3 roles, 0 file and 0 site problems, no Error Log entries. | E4: Abdul Hakeem
A5: 22 Oct 2026 | B5: Medical HRMS | C5: HR-58, HR-70, JM-05, JM-19, B-42 – B-44, TC-REC-13, TC-REC-14 | D5: develop (Fathir's job application update, PR #2) merged into feature/uat-2026-10-22; conflicts in job_application.py, job-application.html and ar.csv resolved keeping both sides; the Appreciation list restored and the work extension accepted again on the updated form (B-42, B-44); a migrate no longer fails when it overlaps the hourly Jameah refresh (B-43); test output removed from the repository. Re-tested: 95/95 browser checks, 37/37 unit tests, 23/23 Ministry views OK, no Error Log entries. Branch to test and deploy: feature/uat-2026-10-22. | E5: Abdul Hakeem
A6: 22 Oct 2026 | B6: Medical HRMS | C6: HR-08, HR-09, HR-19, HR-20, HR-22, HR-68, HR-69, B-36 – B-40, DEC-14, CL-28 – CL-33 | D6: Leave made one flow: Leave Plan (employees send it; manager and department head approve) -> Leave Application (only leave the employee holds, with the days left; Apply now from an approved plan) -> Leave Return (asked for when a leave ends; certificate and occupational health only after sick leave). Sick-leave types renamed in pay order (Sick Leave 1 / 2 / 3) by a migration patch. HR Portal Leave section: setup check per company, daily leave counts, yearly setup in order. Arabic for 114 new texts. 5 unit tests and 7 browser tests (LV-01 - LV-07); test cases TC-LV-09 - 17, TC-HRD-06/07. Real company Al Riyada College still needs its leave setup (HR-69). Branch to test and deploy: feature/uat-2026-10-22 (all work to date). | E6: Abdul Hakeem
A7: 22 Oct 2026 | B7: Testing | C7: HR-67, B-41 | D7: Browser test suite, QA data scripts and the results helper kept in the repository (tests/e2e); the QA scripts only run on a site named in QA_TEST_SITE. The QA reset no longer leaves the QA HR User without access to its own My Settings (test data only). The leave unit test now attaches a real test file, so it no longer writes 'Error Attaching File' to the Error Log. Full run 22 Oct: 95/95 browser checks, 36/36 unit tests, 23/23 Ministry views OK, no new Error Log entries. | E7: Abdul Hakeem
A8: 21 Oct 2026 | B8: Medical HRMS + Jameah | C8: HR-49, HR-50, HR-51, HR-65, JM-14, B-35, DEC-12, DEC-13 | D8: Report 'Employees Missing Ministry Data'; data sheet for non-academic staff (download, check, import); unused duplicate applicant Ministry fields removed; Create Employee dialog asks for every field the Employee form requires; Jameah Faculty views (8) built and verified (23 views in all). Arabic for the 46 new labels. Documents moved to the project_tracking folder; Checklist workbook added; dates on every row; HRM_TASK_TRACKER.md marked as superseded. | E8: Abdul Hakeem
A9: 21 Oct 2026 | B9: Medical HRMS | C9: HR-66 | D9: HR Portal and Employee Portal in the new college portal design (menu, top bar, EN/AR, dark mode); Arabic translations for these pages. | E9: Abdul Hakeem
A10: 21 Oct 2026 | B10: Medical HRMS + Jameah | C10: HR-12, HR-31, HR-32, HR-45, HR-46, HR-59 – HR-64, JM-17, JM-18, B-24 – B-34 | D10: End-to-end test round 3 with an error sweep of every page: fixes for the errors the client reported (non-Saudi employees, breadcrumb 'Not permitted', Cost Center pop-up, academic hire e-mail, Holiday List); HR login lands on the HR Dashboard; Ministry GPA and credit hours from Education's official calculation. Test Report, Test Cases and Task Tracker created. | E10: Abdul Hakeem
A11: 20 Oct 2026 | B11: Medical HRMS + Jameah | C11: HR-07 – HR-09, HR-13 – HR-15, HR-19, HR-22, HR-26, HR-36 – HR-44, JM-02 – JM-07, B-12 – B-23 | D11: Jameah Employee (5) and Student (10) views built and verified value by value; Academic Presence; browser test round 2 fixes. | E11: Abdul Hakeem
A12: 19 Oct 2026 | B12: Medical HRMS + Jameah | C12: HR-02, HR-05, HR-06, HR-24, HR-27, HR-33 – HR-35, JM-01, B-01 – B-11 | D12: Browser end-to-end test round 1 and fixes (approvals, recruitment security, Ministry identity rules); Instructor data sheet; Jameah research. | E12: Abdul Hakeem
A13: 1 Oct 2026 | B13: Medical HRMS | C13: HR-01 – HR-32 | D13: First HRM task tracker (HRM_TASK_TRACKER.md / .csv). | E13: Team
