Workbook

Sheet Read Me
B1: Medical HRMS & Jameah — Test Cases
B2: For the testing team · prepared 21 Oct 2026
B4: How to use
B5: 1. Use the test site (not live data) and the accounts in 'Test Accounts'.
B6: 2. Work through 'Test Cases' top to bottom. Fill the yellow columns: Result, Tested By, Test Date, Actual Result / Notes, Bug ID.
B7: 3. Every Fail or error pop-up gets a row in 'Bug Report' — with the exact date and time, the page address and the exact message. The client sees an error at unknown times, so the time and page are the most important facts.
B8: 4. 'Summary' counts results by module automatically.
B10: Columns
B11: Last automated run | C11: Result of the same check in the developer's automated browser run. A case can pass there and still fail for you — please test it anyway.
B12: Priority | C12: Critical: blocks go-live. High: must work for UAT. Medium / Low: fix before or soon after go-live.
B13: Type | C13: Functional, Negative (wrong input must be refused), Security, Regression (a bug that was fixed), Usability, Monitoring, Data.
B15: Result values
B16: Not run
B17: Pass
B18: Fail
B19: Blocked
B20: N/A

Sheet Summary
A1: Test summary
A2: Counts are formulas over the Test Cases sheet; they update as testers fill the Result column.
A4: Module | B4: Cases | C4: Not run | D4: Pass | E4: Fail | F4: Blocked | G4: N/A | H4: % passed (of run) | I4: Critical not passed
A5: Login & landing | B5: =COUNTIF('Test Cases'!$B$2:$B$304,$A5) | C5: =COUNTIFS('Test Cases'!$B$2:$B$304,$A5,'Test Cases'!$M$2:$M$304,C$4) | D5: =COUNTIFS('Test Cases'!$B$2:$B$304,$A5,'Test Cases'!$M$2:$M$304,D$4) | E5: =COUNTIFS('Test Cases'!$B$2:$B$304,$A5,'Test Cases'!$M$2:$M$304,E$4) | F5: =COUNTIFS('Test Cases'!$B$2:$B$304,$A5,'Test Cases'!$M$2:$M$304,F$4) | G5: =COUNTIFS('Test Cases'!$B$2:$B$304,$A5,'Test Cases'!$M$2:$M$304,G$4) | H5: =IFERROR(D5/(D5+E5+F5),"-") | I5: =COUNTIFS('Test Cases'!$B$2:$B$304,$A5,'Test Cases'!$I$2:$I$304,"Critical")-COUNTIFS('Test Cases'!$B$2:$B$304,$A5,'Test Cases'!$I$2:$I$304,"Critical",'Test Cases'!$M$2:$M$304,"Pass")
A6: HR Dashboard | B6: =COUNTIF('Test Cases'!$B$2:$B$304,$A6) | C6: =COUNTIFS('Test Cases'!$B$2:$B$304,$A6,'Test Cases'!$M$2:$M$304,C$4) | D6: =COUNTIFS('Test Cases'!$B$2:$B$304,$A6,'Test Cases'!$M$2:$M$304,D$4) | E6: =COUNTIFS('Test Cases'!$B$2:$B$304,$A6,'Test Cases'!$M$2:$M$304,E$4) | F6: =COUNTIFS('Test Cases'!$B$2:$B$304,$A6,'Test Cases'!$M$2:$M$304,F$4) | G6: =COUNTIFS('Test Cases'!$B$2:$B$304,$A6,'Test Cases'!$M$2:$M$304,G$4) | H6: =IFERROR(D6/(D6+E6+F6),"-") | I6: =COUNTIFS('Test Cases'!$B$2:$B$304,$A6,'Test Cases'!$I$2:$I$304,"Critical")-COUNTIFS('Test Cases'!$B$2:$B$304,$A6,'Test Cases'!$I$2:$I$304,"Critical",'Test Cases'!$M$2:$M$304,"Pass")
A7: Employee self-service | B7: =COUNTIF('Test Cases'!$B$2:$B$304,$A7) | C7: =COUNTIFS('Test Cases'!$B$2:$B$304,$A7,'Test Cases'!$M$2:$M$304,C$4) | D7: =COUNTIFS('Test Cases'!$B$2:$B$304,$A7,'Test Cases'!$M$2:$M$304,D$4) | E7: =COUNTIFS('Test Cases'!$B$2:$B$304,$A7,'Test Cases'!$M$2:$M$304,E$4) | F7: =COUNTIFS('Test Cases'!$B$2:$B$304,$A7,'Test Cases'!$M$2:$M$304,F$4) | G7: =COUNTIFS('Test Cases'!$B$2:$B$304,$A7,'Test Cases'!$M$2:$M$304,G$4) | H7: =IFERROR(D7/(D7+E7+F7),"-") | I7: =COUNTIFS('Test Cases'!$B$2:$B$304,$A7,'Test Cases'!$I$2:$I$304,"Critical")-COUNTIFS('Test Cases'!$B$2:$B$304,$A7,'Test Cases'!$I$2:$I$304,"Critical",'Test Cases'!$M$2:$M$304,"Pass")
A8: Leave | B8: =COUNTIF('Test Cases'!$B$2:$B$304,$A8) | C8: =COUNTIFS('Test Cases'!$B$2:$B$304,$A8,'Test Cases'!$M$2:$M$304,C$4) | D8: =COUNTIFS('Test Cases'!$B$2:$B$304,$A8,'Test Cases'!$M$2:$M$304,D$4) | E8: =COUNTIFS('Test Cases'!$B$2:$B$304,$A8,'Test Cases'!$M$2:$M$304,E$4) | F8: =COUNTIFS('Test Cases'!$B$2:$B$304,$A8,'Test Cases'!$M$2:$M$304,F$4) | G8: =COUNTIFS('Test Cases'!$B$2:$B$304,$A8,'Test Cases'!$M$2:$M$304,G$4) | H8: =IFERROR(D8/(D8+E8+F8),"-") | I8: =COUNTIFS('Test Cases'!$B$2:$B$304,$A8,'Test Cases'!$I$2:$I$304,"Critical")-COUNTIFS('Test Cases'!$B$2:$B$304,$A8,'Test Cases'!$I$2:$I$304,"Critical",'Test Cases'!$M$2:$M$304,"Pass")
A9: HR approvals | B9: =COUNTIF('Test Cases'!$B$2:$B$304,$A9) | C9: =COUNTIFS('Test Cases'!$B$2:$B$304,$A9,'Test Cases'!$M$2:$M$304,C$4) | D9: =COUNTIFS('Test Cases'!$B$2:$B$304,$A9,'Test Cases'!$M$2:$M$304,D$4) | E9: =COUNTIFS('Test Cases'!$B$2:$B$304,$A9,'Test Cases'!$M$2:$M$304,E$4) | F9: =COUNTIFS('Test Cases'!$B$2:$B$304,$A9,'Test Cases'!$M$2:$M$304,F$4) | G9: =COUNTIFS('Test Cases'!$B$2:$B$304,$A9,'Test Cases'!$M$2:$M$304,G$4) | H9: =IFERROR(D9/(D9+E9+F9),"-") | I9: =COUNTIFS('Test Cases'!$B$2:$B$304,$A9,'Test Cases'!$I$2:$I$304,"Critical")-COUNTIFS('Test Cases'!$B$2:$B$304,$A9,'Test Cases'!$I$2:$I$304,"Critical",'Test Cases'!$M$2:$M$304,"Pass")
A10: Security & privacy | B10: =COUNTIF('Test Cases'!$B$2:$B$304,$A10) | C10: =COUNTIFS('Test Cases'!$B$2:$B$304,$A10,'Test Cases'!$M$2:$M$304,C$4) | D10: =COUNTIFS('Test Cases'!$B$2:$B$304,$A10,'Test Cases'!$M$2:$M$304,D$4) | E10: =COUNTIFS('Test Cases'!$B$2:$B$304,$A10,'Test Cases'!$M$2:$M$304,E$4) | F10: =COUNTIFS('Test Cases'!$B$2:$B$304,$A10,'Test Cases'!$M$2:$M$304,F$4) | G10: =COUNTIFS('Test Cases'!$B$2:$B$304,$A10,'Test Cases'!$M$2:$M$304,G$4) | H10: =IFERROR(D10/(D10+E10+F10),"-") | I10: =COUNTIFS('Test Cases'!$B$2:$B$304,$A10,'Test Cases'!$I$2:$I$304,"Critical")-COUNTIFS('Test Cases'!$B$2:$B$304,$A10,'Test Cases'!$I$2:$I$304,"Critical",'Test Cases'!$M$2:$M$304,"Pass")
A11: Employee master & Ministry fields | B11: =COUNTIF('Test Cases'!$B$2:$B$304,$A11) | C11: =COUNTIFS('Test Cases'!$B$2:$B$304,$A11,'Test Cases'!$M$2:$M$304,C$4) | D11: =COUNTIFS('Test Cases'!$B$2:$B$304,$A11,'Test Cases'!$M$2:$M$304,D$4) | E11: =COUNTIFS('Test Cases'!$B$2:$B$304,$A11,'Test Cases'!$M$2:$M$304,E$4) | F11: =COUNTIFS('Test Cases'!$B$2:$B$304,$A11,'Test Cases'!$M$2:$M$304,F$4) | G11: =COUNTIFS('Test Cases'!$B$2:$B$304,$A11,'Test Cases'!$M$2:$M$304,G$4) | H11: =IFERROR(D11/(D11+E11+F11),"-") | I11: =COUNTIFS('Test Cases'!$B$2:$B$304,$A11,'Test Cases'!$I$2:$I$304,"Critical")-COUNTIFS('Test Cases'!$B$2:$B$304,$A11,'Test Cases'!$I$2:$I$304,"Critical",'Test Cases'!$M$2:$M$304,"Pass")
A12: Medical licences | B12: =COUNTIF('Test Cases'!$B$2:$B$304,$A12) | C12: =COUNTIFS('Test Cases'!$B$2:$B$304,$A12,'Test Cases'!$M$2:$M$304,C$4) | D12: =COUNTIFS('Test Cases'!$B$2:$B$304,$A12,'Test Cases'!$M$2:$M$304,D$4) | E12: =COUNTIFS('Test Cases'!$B$2:$B$304,$A12,'Test Cases'!$M$2:$M$304,E$4) | F12: =COUNTIFS('Test Cases'!$B$2:$B$304,$A12,'Test Cases'!$M$2:$M$304,F$4) | G12: =COUNTIFS('Test Cases'!$B$2:$B$304,$A12,'Test Cases'!$M$2:$M$304,G$4) | H12: =IFERROR(D12/(D12+E12+F12),"-") | I12: =COUNTIFS('Test Cases'!$B$2:$B$304,$A12,'Test Cases'!$I$2:$I$304,"Critical")-COUNTIFS('Test Cases'!$B$2:$B$304,$A12,'Test Cases'!$I$2:$I$304,"Critical",'Test Cases'!$M$2:$M$304,"Pass")
A13: Recruitment | B13: =COUNTIF('Test Cases'!$B$2:$B$304,$A13) | C13: =COUNTIFS('Test Cases'!$B$2:$B$304,$A13,'Test Cases'!$M$2:$M$304,C$4) | D13: =COUNTIFS('Test Cases'!$B$2:$B$304,$A13,'Test Cases'!$M$2:$M$304,D$4) | E13: =COUNTIFS('Test Cases'!$B$2:$B$304,$A13,'Test Cases'!$M$2:$M$304,E$4) | F13: =COUNTIFS('Test Cases'!$B$2:$B$304,$A13,'Test Cases'!$M$2:$M$304,F$4) | G13: =COUNTIFS('Test Cases'!$B$2:$B$304,$A13,'Test Cases'!$M$2:$M$304,G$4) | H13: =IFERROR(D13/(D13+E13+F13),"-") | I13: =COUNTIFS('Test Cases'!$B$2:$B$304,$A13,'Test Cases'!$I$2:$I$304,"Critical")-COUNTIFS('Test Cases'!$B$2:$B$304,$A13,'Test Cases'!$I$2:$I$304,"Critical",'Test Cases'!$M$2:$M$304,"Pass")
A14: Academic presence | B14: =COUNTIF('Test Cases'!$B$2:$B$304,$A14) | C14: =COUNTIFS('Test Cases'!$B$2:$B$304,$A14,'Test Cases'!$M$2:$M$304,C$4) | D14: =COUNTIFS('Test Cases'!$B$2:$B$304,$A14,'Test Cases'!$M$2:$M$304,D$4) | E14: =COUNTIFS('Test Cases'!$B$2:$B$304,$A14,'Test Cases'!$M$2:$M$304,E$4) | F14: =COUNTIFS('Test Cases'!$B$2:$B$304,$A14,'Test Cases'!$M$2:$M$304,F$4) | G14: =COUNTIFS('Test Cases'!$B$2:$B$304,$A14,'Test Cases'!$M$2:$M$304,G$4) | H14: =IFERROR(D14/(D14+E14+F14),"-") | I14: =COUNTIFS('Test Cases'!$B$2:$B$304,$A14,'Test Cases'!$I$2:$I$304,"Critical")-COUNTIFS('Test Cases'!$B$2:$B$304,$A14,'Test Cases'!$I$2:$I$304,"Critical",'Test Cases'!$M$2:$M$304,"Pass")
A15: Jameah (Ministry) | B15: =COUNTIF('Test Cases'!$B$2:$B$304,$A15) | C15: =COUNTIFS('Test Cases'!$B$2:$B$304,$A15,'Test Cases'!$M$2:$M$304,C$4) | D15: =COUNTIFS('Test Cases'!$B$2:$B$304,$A15,'Test Cases'!$M$2:$M$304,D$4) | E15: =COUNTIFS('Test Cases'!$B$2:$B$304,$A15,'Test Cases'!$M$2:$M$304,E$4) | F15: =COUNTIFS('Test Cases'!$B$2:$B$304,$A15,'Test Cases'!$M$2:$M$304,F$4) | G15: =COUNTIFS('Test Cases'!$B$2:$B$304,$A15,'Test Cases'!$M$2:$M$304,G$4) | H15: =IFERROR(D15/(D15+E15+F15),"-") | I15: =COUNTIFS('Test Cases'!$B$2:$B$304,$A15,'Test Cases'!$I$2:$I$304,"Critical")-COUNTIFS('Test Cases'!$B$2:$B$304,$A15,'Test Cases'!$I$2:$I$304,"Critical",'Test Cases'!$M$2:$M$304,"Pass")
A16: Errors & monitoring | B16: =COUNTIF('Test Cases'!$B$2:$B$304,$A16) | C16: =COUNTIFS('Test Cases'!$B$2:$B$304,$A16,'Test Cases'!$M$2:$M$304,C$4) | D16: =COUNTIFS('Test Cases'!$B$2:$B$304,$A16,'Test Cases'!$M$2:$M$304,D$4) | E16: =COUNTIFS('Test Cases'!$B$2:$B$304,$A16,'Test Cases'!$M$2:$M$304,E$4) | F16: =COUNTIFS('Test Cases'!$B$2:$B$304,$A16,'Test Cases'!$M$2:$M$304,F$4) | G16: =COUNTIFS('Test Cases'!$B$2:$B$304,$A16,'Test Cases'!$M$2:$M$304,G$4) | H16: =IFERROR(D16/(D16+E16+F16),"-") | I16: =COUNTIFS('Test Cases'!$B$2:$B$304,$A16,'Test Cases'!$I$2:$I$304,"Critical")-COUNTIFS('Test Cases'!$B$2:$B$304,$A16,'Test Cases'!$I$2:$I$304,"Critical",'Test Cases'!$M$2:$M$304,"Pass")
A17: All modules | B17: =SUM(B5:B16) | C17: =SUM(C5:C16) | D17: =SUM(D5:D16) | E17: =SUM(E5:E16) | F17: =SUM(F5:F16) | G17: =SUM(G5:G16) | H17: =IFERROR(D17/(D17+E17+F17),"-") | I17: =SUM(I5:I16)
A19: Last automated run (developer)
A20: Pass | B20: =COUNTIF('Test Cases'!$L$2:$L$304,"Pass")
A21: Fail | B21: =COUNTIF('Test Cases'!$L$2:$L$304,"Fail")
A22: Manual only / unit test | B22: =COUNTA('Test Cases'!$L$2:$L$104)-B20-B21

Sheet Test Cases
A1: TC ID | B1: Module | C1: Scenario | D1: Login / role | E1: Preconditions | F1: Steps | G1: Test data | H1: Expected result | I1: Priority | J1: Type | K1: Automated test | L1: Last automated run | M1: Result | N1: Tested by | O1: Test date | P1: Actual result / notes | Q1: Bug ID
A2: TC-LGN-01 | B2: Login & landing | C2: HR Manager lands on the HR Dashboard | D2: HR Manager | E2: HR Manager login exists. | F2: 1. Open /login. 2. Enter HR Manager e-mail and password. 3. Click Login. | G2: HR Manager account | H2: The HR Dashboard opens (/app/hr-dashboard) showing 'Welcome back, HR Team'. No error pop-up. | I2: Critical | J2: Functional | K2: LGN-01 | L2: Pass | M2: Not run
A3: TC-LGN-02 | B3: Login & landing | C3: HR User lands on the HR Dashboard | D3: HR User | E3: HR User login exists. | F3: Same as TC-LGN-01 with the HR User account. | G3: HR User account | H3: HR Dashboard opens. | I3: High | J3: Functional | K3: LGN-02 | L3: Pass | M3: Not run
A4: TC-LGN-03 | B4: Login & landing | C4: Employee lands on the Employee Dashboard | D4: Employee | E4: Employee login linked to an Employee record. | F4: Log in as the employee. | G4: Employee account | H4: Employee Dashboard opens with their name and Employee ID. | I4: Critical | J4: Functional | K4: LGN-03 | L4: Pass | M4: Not run
A5: TC-LGN-04 | B5: Login & landing | C5: Instructor keeps the Instructor dashboard | D5: Instructor | E5: Instructor login. | F5: Log in as the instructor. | G5: Instructor account | H5: Instructor Portal opens (not the HR or Employee dashboard). | I5: High | J5: Regression | K5: LGN-04 | L5: Pass | M5: Not run
A6: TC-LGN-05 | B6: Login & landing | C6: Opening /app again returns to the user's dashboard | D6: HR Manager | E6: Logged in. | F6: 1. Open a new browser tab. 2. Go to /app. | G6: — | H6: The same dashboard opens again. | I6: Medium | J6: Functional | K6: LGN-01..04 | L6: Pass | M6: Not run
A7: TC-LGN-06 | B7: Login & landing | C7: Wrong password | D7: Applicant (not logged in) | E7: — | F7: 1. Open /login. 2. Enter a valid e-mail and a wrong password. 3. Click Login. | G7: Wrong password | H7: An 'invalid login' message; stays on the login page. | I7: Medium | J7: Negative | K7: LGN-05 | L7: Pass | M7: Not run
A8: TC-LGN-07 | B8: Login & landing | C8: Logout and log in as a different role | D8: HR Manager | E8: Logged in as HR. | F8: 1. Log out. 2. Log in as an employee. | G8: Two accounts | H8: Employee lands on the Employee Dashboard; no HR pages are shown. | I8: Medium | J8: Functional | K8: — | L8: Manual only | M8: Not run
A9: TC-LGN-08 | B9: Login & landing | C9: Breadcrumbs never lead to 'Not permitted' | D9: Employee | E9: Logged in as an employee. | F9: 1. Open the Employee Dashboard, Leave Application list and a request list. 2. Click every link in the top bar next to the logo (breadcrumbs). | G9: — | H9: Each breadcrumb opens a page the employee can see (e.g. Employee Self Service). Never 'Not permitted'. | I9: High | J9: Regression | K9: NAV-01 | L9: Pass | M9: Not run
A10: TC-LGN-09 | B10: Login & landing | C10: HR breadcrumbs | D10: HR Manager | E10: Logged in as HR. | F10: Same as TC-LGN-08 as HR. | G10: — | H10: Breadcrumbs open (Medical HRMS, HR...). | I10: Medium | J10: Regression | K10: NAV-02 | L10: Pass | M10: Not run
A11: TC-LGN-10 | B11: Login & landing | C11: New portal design: menu, top bar, heading | D11: HR Manager | E11: Logged in as HR. | F11: 1. Look at the left menu, the top bar and the heading. 2. Open each menu section (Employee Requests, Leave ...) and a few pages from it. 3. Click 'Collapse menu', then expand it again. | G11: — | H11: Same style as the Instructor Portal: dark-green menu with sections, breadcrumb 'HR Portal / Dashboard', EN/AR, moon icon, bell and initials on the top bar. Every menu page opens (no 'Not permitted'). | I11: High | J11: Functional | K11: HRD-03 | L11: Pass | M11: Not run
A12: TC-LGN-11 | B12: Login & landing | C12: Employee Portal menu actions | D12: Employee | E12: Logged in as an employee. | F12: 1. Menu > New Request > Permission Request. 2. Menu > My Leave and Recent Requests. 3. Menu > My Profile. | G12: — | H12: 1 opens the Permission Request form; 2 scrolls to that section; 3 shows your profile. No HR entries in the menu. | I12: High | J12: Functional | K12: SHL-01 | L12: Pass | M12: Not run
A13: TC-LGN-12 | B13: Login & landing | C13: Dark mode and Arabic from the top bar | D13: Employee | E13: Logged in. | F13: 1. Click the moon icon; click it again. 2. Click AR; check the page; click EN. | G13: — | H13: Dark mode switches on and off. In Arabic the menu moves to the right and labels are in Arabic; EN switches back. | I13: Medium | J13: Functional | K13: SHL-05 | L13: Pass | M13: Not run
... A104: TC-ERR-04 | B104: Errors & monitoring | C104: Browser console during testing | D104: Any | E104: Chrome DevTools open (F12 -> Console). | F104: Use the system as normal while the console is open. | G104: — | H104: No red errors. If one appears, screenshot the console and record the time and page. | I104: Medium | J104: Monitoring | K104: Error sweep SWP-01..04 | L104: Pass | M104: Not run

Sheet Bug Report
A1: Bug ID | B1: Date & time seen | C1: Login (user) | D1: Role | E1: Page address (URL) | F1: What you were doing (steps) | G1: Exact error message | H1: Screenshot file name | I1: Browser / device | J1: Severity | K1: TC ID | L1: Status | M1: Developer notes
A2: BUG-001 | B2: 2026-10-22 10:35 | C2: hr.user@alriyada.edu.sa | D2: HR User | E2: https://<site>/app/leave-application/HR-LAP-2026-00012 | F2: Opened the leave, set Status to Approved, clicked Save | G2: Example: 'Insufficient Permission for Leave Application' (red pop-up) | H2: bug-001.png | I2: Chrome 130 / Windows | J2: High | K2: TC-LV-02 | L2: Open | M2: Example row — replace with real reports

Sheet Test Accounts
A1: Role | B1: What it is for | C1: Account on the test site | D1: Notes
A2: HR Manager | B2: HR Dashboard, approvals, recruitment, Jameah pages | C2: Ask the developer (QA accounts are created per test run) | D2: Must have HR Manager + HR User roles
A3: HR User | B3: Day-to-day HR checks | C3: Ask the developer | D3: HR User role only
A4: Employee (x2) | B4: Self-service and privacy checks (two people) | C4: Ask the developer | D4: Each must be linked to an Employee record with a leave approver
A5: Instructor | B5: Check the Instructor dashboard is not affected | C5: qa.instructor@rchs-qa.test / QaInstructor#2026 | D5: Local test site only
A6: Academic Affairs (Education Manager) | B6: Jameah Settings and Code Map | C6: Ask the developer | D6: Education Manager role
A7: Administrator | B7: Error Log, e-mail account, scheduled jobs | C7: Site administrator | D7: Never use for normal test cases
A8: Applicant | B8: Public job application form | C8: No login — use the generated link | D8: Use test e-mails, never real people

Sheet Owner Checks
A1: ID | B1: Area | C1: Check | D1: How | E1: When | F1: Done? (Yes/No) | G1: Notes
A2: OC-01 | B2: Production server | C2: Error Log on the live server | D2: Open /app/error-log on the live site; group by title; note the times. This is where the client's 'random' error will be. | E2: Before UAT
A3: OC-02 | B3: Production server | C3: System e-mail account | D3: Email Account 'Notifications' -> re-enter the password -> Save -> send a test mail. Fixes 'Failed to decrypt key ...password' (seen 10 times on this copy). | E3: Before UAT
A4: OC-03 | B4: Production server | C4: Deploy and migrate | D4: Pull the medical_hrms branch, bench migrate, restart. Watch the migrate output for errors. | E4: Deployment
A5: OC-04 | B5: Production server | C5: Scheduler and long-queue worker running | D5: bench --site <site> doctor; the hourly Jameah refresh now runs on the long queue (~7 min), so a long-queue worker must be running. | E5: After deploy
A6: OC-05 | B6: Production server | C6: Logo file | D6: Open /files/rchs-logo.png on the live site; upload it again if missing. | E6: Before UAT
A7: OC-06 | B7: Real accounts | C7: Real HR login | D7: Log in with a real HR account (or Impersonate from Administrator) and confirm the HR Dashboard opens. | E7: After deploy
A8: OC-07 | B8: Real accounts | C8: Real instructor / HOD / advisor login | D8: Impersonate one of each and confirm their dashboards still open (the HR redirect must not change them). | E8: After deploy
A9: OC-08 | B9: Jameah | C9: Ministry view names | D9: Ask the Ministry contact which view/column names the Jameah agent reads (DEC-01). | E9: Before go-live
A10: OC-09 | B10: Jameah | C10: Read-only DB account | D10: Create it with grant_statements; give the Ministry the connection details. | E10: Before go-live
A11: OC-10 | B11: Data | C11: Settings and code decisions | D11: Get answers for DEC-02..DEC-07 from Academic Affairs and enter them (Jameah Settings, Code Map). | E11: Before go-live
A12: OC-11 | B12: Education repo | C12: Education branch on master | D12: The education checkout is on master and 4 commits behind origin; pull with --ff-only before testing. | E12: Now
A13: OC-12 | B13: Browser | C13: Arabic interface | D13: Switch to Arabic and repeat a few test cases (HR Dashboard, Employee Dashboard, application form). | E13: UAT
... A15: OC-14 | B15: Jameah | C15: Verify the views on the live server | D15: bench --site <site> execute medical_hrms.jameah.verify.run -> all 15 views OK. Do this after the Education master update is deployed too: GPA and hours now come from Education's official calculation. | E15: After deploy
