Workbook

Sheet Read Me
B1: Medical HRMS & Jameah — Task Tracker
B2: Al-Riyada College for Health Sciences · status as of 21 Oct 2026
B4: What this workbook is
B5: One place to see what has been done on Medical HRMS (HR system) and Jameah (Ministry of Education data), what is being done now, and what is still pending.
B6: It continues the 1 Oct 2026 tracker (HRM_TASK_TRACKER.md / .csv): tasks HR-01 to HR-32 keep their IDs and are updated; HR-33 onwards and JM-01 onwards are new.
B8: Sheets
B9: Summary | C9: Counts by status, workstream and date. Updates by itself when you change a status in Tasks.
B10: Tasks | C10: Every task: when it was done, status, owner, evidence and the next step. Filter on any column.
B11: Bugs | C11: Every bug found during testing, its cause, the fix and how it was verified.
B12: Decisions | C12: Questions only the college, the Ministry or another team can answer. Yellow columns are for the answer.
B14: Status values
B15: Done | C15: Built and tested.
B16: Done – client UAT pending | C16: Built and tested by the team; waiting for HR/client acceptance testing.
B17: In progress | C17: Being worked on.
B18: Pending – decision needed | C18: Waiting for an answer (see Decisions).
B19: Pending – data / setup | C19: Code is ready; needs data entry or server setup.
B20: Pending – development | C20: Not built yet.
B21: Pending – other team | C21: Needs the Education team, Finance or another party.
B22: Planned | C22: Agreed for later; not started.
B24: How to update
B25: Change the Status cell in Tasks (it has a drop-down). Add new tasks at the bottom with the next free ID. Summary and colours update automatically.
B27: Sources
B28: HRM_TASK_TRACKER.md/.csv, HRM_UAT_SCENARIOS.md, HRM_APPROVAL_MATRIX.md, JAMEAH_HRMS_* documents, MINISTRY_FIELD_MAPPING.html, Ministry schema V0.1, git history of medical_hrms (phpdevpro/edu-alriyada-hrm), test runs of 19–21 Oct 2026.
B29: Companion files: Medical_HRMS_Jameah_Test_Cases.xlsx (for the testing team) and the Test Report.

Sheet Summary
A1: Summary
A2: Counts are formulas over the Tasks and Bugs sheets. As of 21 Oct 2026.
A4: Tasks by status | B4: Tasks
A5: Done | B5: =COUNTIF(Tasks!$E$2:$E$285,A5)
A6: Done – client UAT pending | B6: =COUNTIF(Tasks!$E$2:$E$285,A6)
A7: In progress | B7: =COUNTIF(Tasks!$E$2:$E$285,A7)
A8: Pending – decision needed | B8: =COUNTIF(Tasks!$E$2:$E$285,A8)
A9: Pending – data / setup | B9: =COUNTIF(Tasks!$E$2:$E$285,A9)
A10: Pending – development | B10: =COUNTIF(Tasks!$E$2:$E$285,A10)
A11: Pending – other team | B11: =COUNTIF(Tasks!$E$2:$E$285,A11)
A12: Planned | B12: =COUNTIF(Tasks!$E$2:$E$285,A12)
A13: Total tasks | B13: =SUM(B5:B12)
A15: Medical HRMS vs Jameah | B15: Done (both Done statuses) | C15: Open (everything else) | D15: Total
A16: Medical HRMS (HR-…) | B16: =COUNTIFS(Tasks!$A$2:$A$285,"HR-*",Tasks!$E$2:$E$285,"Done")+COUNTIFS(Tasks!$A$2:$A$285,"HR-*",Tasks!$E$2:$E$285,"Done – client UAT pending") | C16: =D16-B16 | D16: =COUNTIF(Tasks!$A$2:$A$285,"HR-*")
A17: Jameah (JM-…) | B17: =COUNTIFS(Tasks!$A$2:$A$285,"JM-*",Tasks!$E$2:$E$285,"Done")+COUNTIFS(Tasks!$A$2:$A$285,"JM-*",Tasks!$E$2:$E$285,"Done – client UAT pending") | C17: =D17-B17 | D17: =COUNTIF(Tasks!$A$2:$A$285,"JM-*")
A19: Work done by date | B19: Tasks
A20: Earlier (May – 5 Oct 2026) | B20: =COUNTIF(Tasks!$D$2:$D$285,"Earlier (May – 5 Oct 2026)")
A21: 19 Oct 2026 | B21: =COUNTIF(Tasks!$D$2:$D$285,"19 Oct 2026")
A22: 20 Oct 2026 | B22: =COUNTIF(Tasks!$D$2:$D$285,"20 Oct 2026")
A23: 21 Oct 2026 | B23: =COUNTIF(Tasks!$D$2:$D$285,"21 Oct 2026")
A24: — (not done yet) | B24: =COUNTIF(Tasks!$D$2:$D$285,"—")
A26: Workstream | B26: Done | C26: Done – client UAT pending | D26: In progress | E26: Pending – decision needed | F26: Pending – data / setup | G26: Pending – development | H26: Pending – other team | I26: Planned | J26: Total
A27: Foundation | B27: =COUNTIFS(Tasks!$B$2:$B$285,$A27,Tasks!$E$2:$E$285,B$26) | C27: =COUNTIFS(Tasks!$B$2:$B$285,$A27,Tasks!$E$2:$E$285,C$26) | D27: =COUNTIFS(Tasks!$B$2:$B$285,$A27,Tasks!$E$2:$E$285,D$26) | E27: =COUNTIFS(Tasks!$B$2:$B$285,$A27,Tasks!$E$2:$E$285,E$26) | F27: =COUNTIFS(Tasks!$B$2:$B$285,$A27,Tasks!$E$2:$E$285,F$26) | G27: =COUNTIFS(Tasks!$B$2:$B$285,$A27,Tasks!$E$2:$E$285,G$26) | H27: =COUNTIFS(Tasks!$B$2:$B$285,$A27,Tasks!$E$2:$E$285,H$26) | I27: =COUNTIFS(Tasks!$B$2:$B$285,$A27,Tasks!$E$2:$E$285,I$26) | J27: =COUNTIF(Tasks!$B$2:$B$285,$A27)
A28: Master data | B28: =COUNTIFS(Tasks!$B$2:$B$285,$A28,Tasks!$E$2:$E$285,B$26) | C28: =COUNTIFS(Tasks!$B$2:$B$285,$A28,Tasks!$E$2:$E$285,C$26) | D28: =COUNTIFS(Tasks!$B$2:$B$285,$A28,Tasks!$E$2:$E$285,D$26) | E28: =COUNTIFS(Tasks!$B$2:$B$285,$A28,Tasks!$E$2:$E$285,E$26) | F28: =COUNTIFS(Tasks!$B$2:$B$285,$A28,Tasks!$E$2:$E$285,F$26) | G28: =COUNTIFS(Tasks!$B$2:$B$285,$A28,Tasks!$E$2:$E$285,G$26) | H28: =COUNTIFS(Tasks!$B$2:$B$285,$A28,Tasks!$E$2:$E$285,H$26) | I28: =COUNTIFS(Tasks!$B$2:$B$285,$A28,Tasks!$E$2:$E$285,I$26) | J28: =COUNTIF(Tasks!$B$2:$B$285,$A28)
A29: Registration | B29: =COUNTIFS(Tasks!$B$2:$B$285,$A29,Tasks!$E$2:$E$285,B$26) | C29: =COUNTIFS(Tasks!$B$2:$B$285,$A29,Tasks!$E$2:$E$285,C$26) | D29: =COUNTIFS(Tasks!$B$2:$B$285,$A29,Tasks!$E$2:$E$285,D$26) | E29: =COUNTIFS(Tasks!$B$2:$B$285,$A29,Tasks!$E$2:$E$285,E$26) | F29: =COUNTIFS(Tasks!$B$2:$B$285,$A29,Tasks!$E$2:$E$285,F$26) | G29: =COUNTIFS(Tasks!$B$2:$B$285,$A29,Tasks!$E$2:$E$285,G$26) | H29: =COUNTIFS(Tasks!$B$2:$B$285,$A29,Tasks!$E$2:$E$285,H$26) | I29: =COUNTIFS(Tasks!$B$2:$B$285,$A29,Tasks!$E$2:$E$285,I$26) | J29: =COUNTIF(Tasks!$B$2:$B$285,$A29)
A30: Recruitment | B30: =COUNTIFS(Tasks!$B$2:$B$285,$A30,Tasks!$E$2:$E$285,B$26) | C30: =COUNTIFS(Tasks!$B$2:$B$285,$A30,Tasks!$E$2:$E$285,C$26) | D30: =COUNTIFS(Tasks!$B$2:$B$285,$A30,Tasks!$E$2:$E$285,D$26) | E30: =COUNTIFS(Tasks!$B$2:$B$285,$A30,Tasks!$E$2:$E$285,E$26) | F30: =COUNTIFS(Tasks!$B$2:$B$285,$A30,Tasks!$E$2:$E$285,F$26) | G30: =COUNTIFS(Tasks!$B$2:$B$285,$A30,Tasks!$E$2:$E$285,G$26) | H30: =COUNTIFS(Tasks!$B$2:$B$285,$A30,Tasks!$E$2:$E$285,H$26) | I30: =COUNTIFS(Tasks!$B$2:$B$285,$A30,Tasks!$E$2:$E$285,I$26) | J30: =COUNTIF(Tasks!$B$2:$B$285,$A30)
A31: HR dashboard | B31: =COUNTIFS(Tasks!$B$2:$B$285,$A31,Tasks!$E$2:$E$285,B$26) | C31: =COUNTIFS(Tasks!$B$2:$B$285,$A31,Tasks!$E$2:$E$285,C$26) | D31: =COUNTIFS(Tasks!$B$2:$B$285,$A31,Tasks!$E$2:$E$285,D$26) | E31: =COUNTIFS(Tasks!$B$2:$B$285,$A31,Tasks!$E$2:$E$285,E$26) | F31: =COUNTIFS(Tasks!$B$2:$B$285,$A31,Tasks!$E$2:$E$285,F$26) | G31: =COUNTIFS(Tasks!$B$2:$B$285,$A31,Tasks!$E$2:$E$285,G$26) | H31: =COUNTIFS(Tasks!$B$2:$B$285,$A31,Tasks!$E$2:$E$285,H$26) | I31: =COUNTIFS(Tasks!$B$2:$B$285,$A31,Tasks!$E$2:$E$285,I$26) | J31: =COUNTIF(Tasks!$B$2:$B$285,$A31)
A32: Self-service | B32: =COUNTIFS(Tasks!$B$2:$B$285,$A32,Tasks!$E$2:$E$285,B$26) | C32: =COUNTIFS(Tasks!$B$2:$B$285,$A32,Tasks!$E$2:$E$285,C$26) | D32: =COUNTIFS(Tasks!$B$2:$B$285,$A32,Tasks!$E$2:$E$285,D$26) | E32: =COUNTIFS(Tasks!$B$2:$B$285,$A32,Tasks!$E$2:$E$285,E$26) | F32: =COUNTIFS(Tasks!$B$2:$B$285,$A32,Tasks!$E$2:$E$285,F$26) | G32: =COUNTIFS(Tasks!$B$2:$B$285,$A32,Tasks!$E$2:$E$285,G$26) | H32: =COUNTIFS(Tasks!$B$2:$B$285,$A32,Tasks!$E$2:$E$285,H$26) | I32: =COUNTIFS(Tasks!$B$2:$B$285,$A32,Tasks!$E$2:$E$285,I$26) | J32: =COUNTIF(Tasks!$B$2:$B$285,$A32)
A33: Security | B33: =COUNTIFS(Tasks!$B$2:$B$285,$A33,Tasks!$E$2:$E$285,B$26) | C33: =COUNTIFS(Tasks!$B$2:$B$285,$A33,Tasks!$E$2:$E$285,C$26) | D33: =COUNTIFS(Tasks!$B$2:$B$285,$A33,Tasks!$E$2:$E$285,D$26) | E33: =COUNTIFS(Tasks!$B$2:$B$285,$A33,Tasks!$E$2:$E$285,E$26) | F33: =COUNTIFS(Tasks!$B$2:$B$285,$A33,Tasks!$E$2:$E$285,F$26) | G33: =COUNTIFS(Tasks!$B$2:$B$285,$A33,Tasks!$E$2:$E$285,G$26) | H33: =COUNTIFS(Tasks!$B$2:$B$285,$A33,Tasks!$E$2:$E$285,H$26) | I33: =COUNTIFS(Tasks!$B$2:$B$285,$A33,Tasks!$E$2:$E$285,I$26) | J33: =COUNTIF(Tasks!$B$2:$B$285,$A33)
A34: Leave | B34: =COUNTIFS(Tasks!$B$2:$B$285,$A34,Tasks!$E$2:$E$285,B$26) | C34: =COUNTIFS(Tasks!$B$2:$B$285,$A34,Tasks!$E$2:$E$285,C$26) | D34: =COUNTIFS(Tasks!$B$2:$B$285,$A34,Tasks!$E$2:$E$285,D$26) | E34: =COUNTIFS(Tasks!$B$2:$B$285,$A34,Tasks!$E$2:$E$285,E$26) | F34: =COUNTIFS(Tasks!$B$2:$B$285,$A34,Tasks!$E$2:$E$285,F$26) | G34: =COUNTIFS(Tasks!$B$2:$B$285,$A34,Tasks!$E$2:$E$285,G$26) | H34: =COUNTIFS(Tasks!$B$2:$B$285,$A34,Tasks!$E$2:$E$285,H$26) | I34: =COUNTIFS(Tasks!$B$2:$B$285,$A34,Tasks!$E$2:$E$285,I$26) | J34: =COUNTIF(Tasks!$B$2:$B$285,$A34)
A35: Approvals | B35: =COUNTIFS(Tasks!$B$2:$B$285,$A35,Tasks!$E$2:$E$285,B$26) | C35: =COUNTIFS(Tasks!$B$2:$B$285,$A35,Tasks!$E$2:$E$285,C$26) | D35: =COUNTIFS(Tasks!$B$2:$B$285,$A35,Tasks!$E$2:$E$285,D$26) | E35: =COUNTIFS(Tasks!$B$2:$B$285,$A35,Tasks!$E$2:$E$285,E$26) | F35: =COUNTIFS(Tasks!$B$2:$B$285,$A35,Tasks!$E$2:$E$285,F$26) | G35: =COUNTIFS(Tasks!$B$2:$B$285,$A35,Tasks!$E$2:$E$285,G$26) | H35: =COUNTIFS(Tasks!$B$2:$B$285,$A35,Tasks!$E$2:$E$285,H$26) | I35: =COUNTIFS(Tasks!$B$2:$B$285,$A35,Tasks!$E$2:$E$285,I$26) | J35: =COUNTIF(Tasks!$B$2:$B$285,$A35)
A36: Compliance | B36: =COUNTIFS(Tasks!$B$2:$B$285,$A36,Tasks!$E$2:$E$285,B$26) | C36: =COUNTIFS(Tasks!$B$2:$B$285,$A36,Tasks!$E$2:$E$285,C$26) | D36: =COUNTIFS(Tasks!$B$2:$B$285,$A36,Tasks!$E$2:$E$285,D$26) | E36: =COUNTIFS(Tasks!$B$2:$B$285,$A36,Tasks!$E$2:$E$285,E$26) | F36: =COUNTIFS(Tasks!$B$2:$B$285,$A36,Tasks!$E$2:$E$285,F$26) | G36: =COUNTIFS(Tasks!$B$2:$B$285,$A36,Tasks!$E$2:$E$285,G$26) | H36: =COUNTIFS(Tasks!$B$2:$B$285,$A36,Tasks!$E$2:$E$285,H$26) | I36: =COUNTIFS(Tasks!$B$2:$B$285,$A36,Tasks!$E$2:$E$285,I$26) | J36: =COUNTIF(Tasks!$B$2:$B$285,$A36)
A37: Integration | B37: =COUNTIFS(Tasks!$B$2:$B$285,$A37,Tasks!$E$2:$E$285,B$26) | C37: =COUNTIFS(Tasks!$B$2:$B$285,$A37,Tasks!$E$2:$E$285,C$26) | D37: =COUNTIFS(Tasks!$B$2:$B$285,$A37,Tasks!$E$2:$E$285,D$26) | E37: =COUNTIFS(Tasks!$B$2:$B$285,$A37,Tasks!$E$2:$E$285,E$26) | F37: =COUNTIFS(Tasks!$B$2:$B$285,$A37,Tasks!$E$2:$E$285,F$26) | G37: =COUNTIFS(Tasks!$B$2:$B$285,$A37,Tasks!$E$2:$E$285,G$26) | H37: =COUNTIFS(Tasks!$B$2:$B$285,$A37,Tasks!$E$2:$E$285,H$26) | I37: =COUNTIFS(Tasks!$B$2:$B$285,$A37,Tasks!$E$2:$E$285,I$26) | J37: =COUNTIF(Tasks!$B$2:$B$285,$A37)
A38: Payroll | B38: =COUNTIFS(Tasks!$B$2:$B$285,$A38,Tasks!$E$2:$E$285,B$26) | C38: =COUNTIFS(Tasks!$B$2:$B$285,$A38,Tasks!$E$2:$E$285,C$26) | D38: =COUNTIFS(Tasks!$B$2:$B$285,$A38,Tasks!$E$2:$E$285,D$26) | E38: =COUNTIFS(Tasks!$B$2:$B$285,$A38,Tasks!$E$2:$E$285,E$26) | F38: =COUNTIFS(Tasks!$B$2:$B$285,$A38,Tasks!$E$2:$E$285,F$26) | G38: =COUNTIFS(Tasks!$B$2:$B$285,$A38,Tasks!$E$2:$E$285,G$26) | H38: =COUNTIFS(Tasks!$B$2:$B$285,$A38,Tasks!$E$2:$E$285,H$26) | I38: =COUNTIFS(Tasks!$B$2:$B$285,$A38,Tasks!$E$2:$E$285,I$26) | J38: =COUNTIF(Tasks!$B$2:$B$285,$A38)
... A48: Jameah | B48: =COUNTIFS(Tasks!$B$2:$B$285,$A48,Tasks!$E$2:$E$285,B$26) | C48: =COUNTIFS(Tasks!$B$2:$B$285,$A48,Tasks!$E$2:$E$285,C$26) | D48: =COUNTIFS(Tasks!$B$2:$B$285,$A48,Tasks!$E$2:$E$285,D$26) | E48: =COUNTIFS(Tasks!$B$2:$B$285,$A48,Tasks!$E$2:$E$285,E$26) | F48: =COUNTIFS(Tasks!$B$2:$B$285,$A48,Tasks!$E$2:$E$285,F$26) | G48: =COUNTIFS(Tasks!$B$2:$B$285,$A48,Tasks!$E$2:$E$285,G$26) | H48: =COUNTIFS(Tasks!$B$2:$B$285,$A48,Tasks!$E$2:$E$285,H$26) | I48: =COUNTIFS(Tasks!$B$2:$B$285,$A48,Tasks!$E$2:$E$285,I$26) | J48: =COUNTIF(Tasks!$B$2:$B$285,$A48)
A50: Bugs | B50: Count
A51: Fixed | B51: =COUNTIF(Bugs!$H$2:$H$135,A51)
A52: Open | B52: =COUNTIF(Bugs!$H$2:$H$135,A52)
A53: Open – other team | B53: =COUNTIF(Bugs!$H$2:$H$135,A53)
A54: Open – check server | B54: =COUNTIF(Bugs!$H$2:$H$135,A54)

Sheet Tasks
A1: ID | B1: Workstream | C1: Task | D1: When done | E1: Status | F1: Owner | G1: Priority | H1: Done so far / evidence | I1: Next step / pending | J1: Reference (commit / file)
A2: HR-01 | B2: Foundation | C2: Custom Medical HRMS app and setup scripts | D2: Earlier (May – 5 Oct 2026) | E2: Done | F2: Abdul Hakeem | G2: Medium | H2: App, setup scripts and migration hooks exist. Migration re-run several times on 19–21 Oct without errors or duplicates; Ministry fields, permissions and Jameah views are created on every migrate. | I2: Run the same migration once on the production server. | J2: hooks.py; patches.txt
A3: HR-02 | B3: Master data | C3: Ministry lookup codes and validation | D3: 19 Oct 2026 | E3: Done | F3: Abdul Hakeem | G3: High | H3: 9,867 Ministry codes loaded from the Arabic and Translated workbooks, every code with Arabic and English names (before: 8,330 showed the code as their name). Loaded automatically on migrate. Demo codes remapped and removed. | I3: None. | J3: 277442b; ministry_codes.py; data/ministry_codes.csv
A4: HR-03 | B4: Master data | C4: Institute hierarchy and facility records | D4: Earlier (May – 5 Oct 2026) | E4: Pending – data / setup | F4: HR | G4: Medium | H4: Branch, Agency, Deanery, College, Academic Department and Facility doctypes exist and are linked to Employee/Instructor. | I4: HR to enter the real hierarchy and confirm employee placement. | J4: create_institute_doctypes.py; create_facility_doctype.py
A5: HR-04 | B5: Registration | C5: Job-level setup | D5: Earlier (May – 5 Oct 2026) | E5: In progress | F5: Dinesh | G5: Medium | H5: Work started by Dinesh (commits 2–5 Oct). | I5: Dinesh to confirm scope done and what remains. | J5: HRM_TASK_TRACKER.md
A6: HR-05 | B6: Registration | C6: Employee registration | D6: 19 Oct 2026 | E6: In progress | F6: Dinesh / Abdul Hakeem | G6: High | H6: Ministry identity rules added (national ID 10 digits starting 1 for Saudis, Iqama 10 digits starting 2) and duplicates blocked (same identity number, home ID or job number). Mandatory Ministry fields enforced on save. | I6: Dinesh to confirm remaining registration scope; complete EMP-00001 demo record (HR-53). | J6: 1f88c78; ministry_lookup_validation.py
A7: HR-06 | B7: Recruitment | C7: Job Applicant to Employee transfer | D7: 19 Oct 2026 | E7: Done – client UAT pending | F7: Abdul Hakeem / Dinesh | G7: High | H7: Public application form -> Accept -> Create Employee tested in the browser on 19, 20 and 21 Oct. Creates Employee, login, Instructor / Academic Advisor / HOD records by role. Lost fields fixed on 20 Oct (HR-44). | I7: HR to run one real hire on the test site. | J7: job_application.py; 8390598
A8: HR-07 | B8: Registration | C8: Qualifications, experience and Ministry profile fields | D8: 20 Oct 2026 | E8: Done | F8: Abdul Hakeem | G8: High | H8: Jameah child tables (qualifications, academic experience, previous experience, training, awards, publications) on Employee. 'Appreciation' fixed to use the Ministry grade list on 20 Oct. These feed the Jameah Employee views. | I8: None. | J8: setup_employee_ministry_expected_fields.py; d690cb7
A9: HR-08 | B9: HR dashboard | C9: HR dashboard and leave-management shortcuts | D9: 20 Oct 2026 | E9: Done – client UAT pending | F9: Abdul Hakeem | G9: High | H9: Every dashboard link opens without an error (browser test HRD-03, 21 Oct). Counts fixed on 19 Oct. Academic Presence and Jameah sections added. | I9: HR UAT. | J9: page/hr_dashboard
A10: HR-09 | B10: Self-service | C10: Employee self-service dashboard | D10: 20 Oct 2026 | E10: Done – client UAT pending | F10: Abdul Hakeem | G10: High | H10: All 10 request types, leave request, details view and counters tested in the browser (ESS-01..17). | I10: Employee UAT, including on a phone. | J10: page/employee_dashboard
A11: HR-10 | B11: HR dashboard | C11: Custom workspace styling | D11: Earlier (May – 5 Oct 2026) | E11: Done – client UAT pending | F11: Abdul Hakeem | G11: Low | H11: Workspace renders (browser test HRD-04). | I11: Check long labels and mobile layout during UAT. | J11: public/css/workspace_theme.css
A12: HR-11 | B12: Self-service | C12: Self-service in Instructor, HOD and other staff dashboards | D12: — | E12: Planned | F12: Abdul Hakeem + Education team | G12: High | H12: Not started. Instructors with an Employee record can already use /app/employee-dashboard. | I12: Add the request and leave cards to the Education dashboards (needs the Education team). | J12: HRM_TASK_TRACKER.md
... A85: JM-17 | B85: Jameah | C85: Transcript GPA rounding at exact ties | D85: 21 Oct 2026 | E85: Done | F85: Education team | G85: Low | H85: Resolved by Education's new GPA module (exact half-up rounding); the views now use it (JM-18). | I85: None. | J85: Jameah report

Sheet Bugs
A1: Bug ID | B1: Found on | C1: Area | D1: Problem | E1: Cause | F1: Fix | G1: Commit / task | H1: Status | I1: How verified
A2: B-01 | B2: 19 Oct 2026 | C2: Travel Request | D2: Every save crashed | E2: Validation read fields that don't exist | F2: Cost read from costings, checked on submit | G2: 91b7697 | H2: Fixed | I2: E2E 19 Oct
A3: B-02 | B3: 19 Oct 2026 | C3: Approvals | D3: Finance approval impossible | E3: Hooks accepted only Finance Manager, which had no access | F3: Accept Finance Manager or Accounts Manager; grant access | G3: 91b7697 | H3: Fixed | I3: E2E 19 Oct
A4: B-03 | B4: 19 Oct 2026 | C4: Return from Leave | D4: Employees could not send the request | E4: Clearance guard compared against the wrong default | F4: Compare with the Select's first option | G4: 91b7697 | H4: Fixed | I4: E2E APR-06
A5: B-04 | B5: 19 Oct 2026 | C5: Children Medical Allowance | D5: Every claim blocked, even drafts | E5: Unused Employee Grade requirement | F5: Requirement removed | G5: 91b7697 | H5: Fixed | I5: E2E ESS-12
A6: B-05 | B6: 19 Oct 2026 | C6: Medical License | D6: Employees could list everyone's licences | E6: No own-record rule | F6: Own-record permission rules | G6: 91b7697 | H6: Fixed | I6: E2E LIC-02
A7: B-06 | B7: 19 Oct 2026 | C7: HR Dashboard | D7: Return-from-leave count always 0 | E7: Doctype name casing | F7: Corrected | G7: 91b7697 | H7: Fixed | I7: E2E HRD-02
A8: B-07 | B8: 19 Oct 2026 | C8: Employee Dashboard | D8: Drafts counted as pending | E8: Status filter | F8: Drafts excluded | G8: 91b7697 | H8: Fixed | I8: E2E ESS-15
A9: B-08 | B9: 19 Oct 2026 | C9: Recruitment (security) | D9: A guest could obtain System Manager via the public form | E9: Role taken from the guest payload | F9: Hireable-role allow-list, server-controlled fields protected | G9: 0ab539e | H9: Fixed | I9: E2E REC-02
A10: B-09 | B10: 19 Oct 2026 | C10: Recruitment | D10: Academic hires landed on dashboards that couldn't find them | E10: Only an Instructor record was created | F10: Records per role (Advisor, HOD...) | G10: 8390598 | H10: Fixed | I10: E2E REC-03/04
A11: B-10 | B11: 19 Oct 2026 | C11: Ministry codes | D11: 8,330 codes showed the code as their name; no Arabic | E11: Importer read only the translated workbook | F11: Merge Arabic + translated workbooks | G11: 277442b | H11: Fixed | I11: Data check
A12: B-11 | B12: 19 Oct 2026 | C12: Registration | D12: Home-country ID required for non-Saudis instead of the Kingdom ID | E12: Wrong rule | F12: Ministry identity rules | G12: 1f88c78 | H12: Fixed | I12: Unit + E2E EMP-05/06
... A35: B-27 | B35: 21 Oct 2026 | C35: Website | D35: Logo file missing (/files/rchs-logo.png) | E35: File not on this copy | F35: Check on the live server | G35: HR-54 | H35: Open – check server | I35: Error sweep

Sheet Decisions
A1: ID | B1: Decision needed | C1: Who decides | D1: Options / recommendation | E1: Blocks tasks | F1: Answer (fill in) | G1: Answered on
A2: DEC-01 | B2: Which view and column names does the Jameah agent read: the HTML names or the Ministry schema V0.1 names? | C2: Ministry contact (Ms. Najah) | D2: Confirm with the Ministry; renaming is a small change. | E2: JM-09, go-live of Jameah
A3: DEC-02 | B3: College code the Ministry assigned to RCHS (College Coding Guide) | C3: Academic Affairs | D3: From the Ministry licence; pick in Jameah Settings. | E3: JM-10
A4: DEC-03 | B4: Study type for regular and for bridging students | C4: Academic Affairs | D4: List includes 0 Total regularity, 7 Bridging. | E4: JM-10
A5: DEC-04 | B5: Program duration and unit | C5: Academic Affairs | D5: From the study plan. | E5: JM-10
A6: DEC-05 | B6: Campus city (Study Location City) | C6: Academic Affairs | D6: Ministry city code, e.g. 0202000 Jeddah Governorate if applicable. | E6: JM-10
A7: DEC-06 | B7: Ministry department and specialization for the nursing program | C7: Academic Affairs | D7: Candidates KL01 Nursing Sciences / KL03 Nursing. | E7: JM-11
A8: DEC-07 | B8: Ministry status for 'Internship' students (238) | C8: Academic Affairs | D8: Most likely 0 'restricted (enrolled)'. | E8: JM-11
A9: DEC-08 | B9: Accept 9-digit identity numbers? | C9: HR + Ministry contact | D9: Today exactly 10 digits for National ID / Iqama. | E9: HR-52
A10: DEC-09 | B10: Approver for each request step and the currency label (SAR) | C10: HR + Finance | D10: Update HRM_APPROVAL_MATRIX.md. | E10: HR-24
A11: DEC-10 | B11: Official holidays and carry-forward rules | C11: HR | D11: Needed for leave and presence. | E11: HR-23, HR-57
A12: DEC-11 | B12: Ministry credit hours: Registered = hours registered this term; Passed = earned + bridged plan hours (so Passed + Remaining = Required, as on the student dashboard). The transcript also shows a lifetime 'registered' total and bridging calc-hours. | C12: Academic Affairs | D12: Recommended as built; confirm with the Ministry definitions. | E12: JM-18
